{
  "venueId": "ChIJpeswiDJ6_ogRTnDdkKSCQ1s",
  "venueName": "California Dreaming",
  "venueArea": "West Ashley",
  "website": "https://californiadreaming.rest/location/Charleston-SC/",
  "scrapedAt": "2026-01-19T15:42:05.086Z",
  "trimmedAt": "2026-01-19T15:49:48.188Z",
  "pages": [
    {
      "url": "https://californiadreaming.rest/location/Charleston-SC/#dropdown",
      "text": "[Page Title: Location - California Dreaming]\n\nLocations + Menus Alabama Spanish Fort Georgia Augusta South Carolina Charleston Columbia Greenville Surside Beach Reserve Menu Order Online Order Online Home Happenings Gift Cards Order Online Contact Locations + Menus Alabama Spanish Fort Georgia Augusta South Carolina Charleston Columbia Greenville Surside Beach Reserve Menu Order Online Order Online Home Happenings Gift Cards Order Online Contact \nCharleston, SC\n\nSince 1987, California Dreaming has been a proud part of the Charleston, SC community. Our spacious, open setting features floor-to-ceiling windows that offer stunning views of the Ashley River, creating the perfect backdrop for a lively night out. You can also enjoy these panoramic views from our wrap-around deck, complete with a bar and easily accessible by boat. Whether you're craving low country favorites or our famous prime rib, California Dreaming is a favorite among both locals and tourists.\nPlease note that we provide Advance Priority Seating to reduce wait times and expedite the seating process when your entire party arrives. To ensure the best experience for all guests, we seat groups of up to 6. While larger groups are seated separately, this arrangement is flexible during quieter hours. 1 Ashley Point Dr \n Charleston, SC 29407 Directions 843.766.1644 Order Now Reserve Hours Open Today Monday 4pm-9pm Sunday 11am-9pm Open Today - Monday 4pm-9pm Tuesday 4pm-9pm Wednesday 4pm-9pm Thursday 4pm-9pm Friday 4pm-10pm Saturday 11am-10pm \n|\nCatering Curbside to-go facebook instagram DINE \nDINE\n| \nDRINK\n| \nWINE\n| \nKIDS\n| \nDESSERT\n| \nASHLEY PATIO\n\nDINE\n\nApps\nShe Crab Soup 9.95 \nA rich and creamy Charleston classic\nSteamed Peel & Eat Shrimp \nOld Bay boil, served with cocktail sauce\n\n1/2lb\n13.95 Fried Crab Claws 17.95 \nServed with spicy cocktail sauce. Limited availability\nSeafood Nachos 18.95 \nSpicy shrimp, salmon, red onions, house-made chips, cheese sauce and lobster cream sauce with dill\nCreamed Spinach Nachos 13.95 \nwith house-made chips\nCalamari 16.95 \nLightly breaded, with marinara\nOysters Rockefeller (4) 17.95 \nSpinach, romano, bacon\nNashville Hot Wings 15.95 \nMarinated in hot pepper sauce, fried crispy, with bleu cheese dip\nChicken Tenders 13.95 \nServed with house-made honey BBQ sauce. cheese dip\nOur Famous Croissants (5) 7.95 \nTopped with honey-butter\nBaked Potato Soup 8.95 \nCreamy soup topped with scallions, cheese, ham and bacon\n\nEntrees\nThe Ashley 24.95 \nBroiled chicken breast, blackened shrimp, lobster cream sauce, served with a side\nRoasted Salmon 27.95 \nEncrusted with rosemary and thyme, served with mashed potatoes and seasonal veggie\nBlackened Chicken Pasta 19.95 \nAlfredo, scallions, tomatoes, with romano cheese\nChicken Tenders Platter 19.95 \nFried chicken tenderloins, served with house-made honey BBQ sauce and french fries\nCrispy Shrimp Tacos (3) 17.95 \nJicama slaw, chipotle mayo, tomatoes, pickled onions, scallions, queso fresco\n\nLow Country Favorites\n\nAdd a house or caesar salad +$5.95\nFirecracker Tuna* 32.95 \nThai glaze, served with mashed potatoes and seasonal veggie\nCrab Cakes 34.95 \nJumbo lump, mustard sauce, served with mashed potatoes and seasonal veggie\nFeatured Fish \nServed with a side item\n\nA.Q.\nCharleston Seafood Pasta 24.95 \nSautéed shrimp, mussels, garlic cream, white wine, romano\nShrimp + Grits 23.95 \nJumbo shrimp, andouille sausage, Adluh Mills grits\n\nFried Seafood Platters\nFried Seafood Platters \nServed with french fries\n\nShrimp\n21.95 \nOysters\n25.95 \nFlounder\n23.95 \nAll Three\n28.95 \nSalads\nCalifornia Dreaming 15.95 \nMixed greens, ham and turkey, cheddar and monterey jack cheeses, egg, tomatoes, almonds topped with warm ham and bacon, house dressing\nRoasted Salmon or Chicken \nMixed greens, bacon, egg, avocado, tomatoes, balsamic vinaigrette\n\nRoasted Salmon\n18.95 \nChicken\n16.95 Caesar \nCrisp romaine with grated romano cheese and croutons\n\nChicken or Fried Shrimp\n15.95 \nFried Oysters\n17.95 \nSteaks, Chops + Ribs\n\nAged USDA Choice | Served with a house or caesar salad and side item. Add broiled or fried shrimp to any steak +$7.95\nPork Chop 26.95 \n16oz. double bone, frenched chop, peach jalapeno jam\nNew York Strip* 39.95 \n14oz. center cut, garlic butter\nSurf + Turf* 34.95 \n10oz. ribeye topped with grilled garlic shrimp\nRibeye* 39.95 \n14oz. hand cut with cajun butter\nFilet Mignon* 40.95 \n8oz. barrel cut\nMarinated Sirloin* 28.95 \n10oz. sirloin marinated in fruit juices, garlic, soy sauce and spices\nBaby Back Ribs \nDanish full-flavored ribs, grilled with a charred exterior, basted with BBQ sauce, with side item\n\nOne Rack\n23.95 \nTwo Racks\n31.95 \nSandwiches & Burgers\n\nServed with french fries\nSpicy Chicken Sandwich 16.95 \nCrispy fried chicken, american cheese, jicama slaw, pickles, chipotle mayo\nNew Orleans Po'boy \nLettuce, tomato and tartar sauce on french bread\n\nFried Shrimp\n16.95 \nFried Oysters\n18.95 Steak Burger* 17.95 \n10 oz., shredded lettuce, pickles, red onion, tomato, cheddar cheese, our signature sauce\nBlackened Mahi Sandwich 17.95 \nToasted brioche, lemon, arugula, ripe tomato, curry mayonnaise, homemade pickles\n\nSides\nFrench Fries 5.95 Seasonal Veggie 5.95 Cole Slaw 5.95 Mashed Potatoes 5.95 Creamed Spinach 5.95 Baked Potato 6.95 \nafter 4pm\n\nDesserts\nChocolate Brownie 9.95 Apple Walnut Cobbler 9.95 Croissant Bread Pudding 9.95 Cheesecake 9.95 \nSeasonal Topping\n\nGluten free - prepared in a fryer with wheat ingredients. *Denotes cooked to order | consuming raw or undercooked meats, poultry, seafood, shellfish or eggs may increase your risk of foodbourne illness especially if you have certain medical conditions\nDisclaimer: Pricing and availability subject to change. \nDRINK\n\nCocktails\nBarrel-Aged Old Fashioned 14.95 \nMaker's Mark 'Living the Dream,' bitters, sugar\nDreamsicle #3 10.95 \nEvan Williams bourbon, Licor 43, vanilla, orange juice\nSpritz-Mas 9.95 \nAperol, cranberry, lemon, prosecco\nHarvest Ember 10.95 \nEvan Williams bourbon, apple butter, lemon, spiced honey, apple wood smoke\n\nMargaritas\n\nPouring: Jose Cuervo Tradicional\nClassic 10.95 \nAgave, lime\nSpiced Cranberry 10.95 \nWhite cranberry, cinnamon, lime, Cointreau\nSmoky Peach 10.95 \nIlegal mezcal, peach, agave, lime\nPineapple Jalapeño 10.95 \nPineapple, jalapeño, lime, triple sec\n\nMartinis\nToasted Marshmallow 11.95 \nHoodoo Espresso vodka, toasted marshmallow infusion\nSugar Cookie 11.95 \nBaileys, Absolut Vanilla vodka, di Amore amaretto\nStrawberry Rose 12.95 \nTito's vodka, rose essence, Chambord, strawberry\nDirty 13.95 \nGrey Goose vodka, olive brine, Dolin dry vermouth\n\nFrozen Drinks\nCali Crush 10.95 \nParrot Bay Coconut rum, blue curacao, pineapple, house sour\nIrish Coffee 10.95 \nJameson whiskey, Kahlua, cream, whipped cream\n\nZero Proof\nCoconut Faux-Jito 9.95 \nNon-Alcoholic, Seedlip Spice 94, Coco Lopez, pineapple, lime, mint\nPineapple Spritz 9.95 \nNon-Alcoholic, Seedlip Grove 42, pineapple, lime, grenadine, cherry\n\nSpirits\n\nBourbon / Whiskey\nBen Holladay 13.95 Bib & Tucker 10yr 15.95 High West High Country 16.95 Blanton's 18.95 Buffalo Trace 9.95 Bulleit Rye 8.95 Eagle Rare 10yr 15.95 Maker's Mark 'Living the Dream' 16.95 Michter's Rye 13.95 Old Forrester 1924 25.95 Old Pepper 11.95 Old Soul Tintype Series #1 19.95 Peerless Rye 19.95 Peg Leg Porker 9.95 Redwood Empire 12.95 Smoke Wagon 16.95 Traveller 13.95 \nTequila\n400 Conejos Mezcal 11.95 Casamigos Reposado 14.95 Don Julio Primavera 29.95 El Tesoro Añejo 13.95 Espolon Blanco 10.95 G4 Blanco 15.95 Herradura Legend 29.95 Lalo Blanco 12.95 Partida Añejo 15.95 Patron Roca Anejo 29.95 Tequila Ocho Plata 12.95 \nBeer\n\nOn Tap\nBlue Moon 6.25 Creature Comforts 6.95 Edmund's Oast 7.95 Michelob Ultra 5.95 Miller Lite 5.95 Modelo Especial 6.25 Southern Hops Blackwater Porter 6.95 \nBottles / Cans\nAustin Eastciders 6.95 Bud Light 5.25 Coors Light 5.25 Corona 5.25 Heineken 6.95 High Rise Pineapple THC Seltzer 9.95 PBR 3.95 Yuengling 5.95 White Claw 6.95 NA Athletic Upside Dawn 7.95 Disclaimer: Pricing and availability subject to change. \nWINE\n\nWhites\nChardonnay, EOS, California 7.95 Chardonnay, Diora, Monterey 9.95 Chardonnay, Buehler, Russian River 11.95 Chardonnay, Frank Family, Carneros, California 55.00 Moscato, Seven Daughters, Italy 8.95 Moscato Rosé, Risata, Italy 7.95 Pinot Grigio, Lunardi, Italy 7.95 Prosecco, Riondo, Italy 8.95 Riesling, Loosen Bros. \"Dr L\" Mosel, Germany 7.95 Sauvignon Blanc, Wairau River, New Zealand 8.95 Sauvignon Blanc, Jax, California 10.95 Sparkling Wine, Poema, Cava 7.95 \nReds\nCabernet Sauvignon, Firestone, Paso Robles 7.95 Cabernet Sauvignon, Leese-Fitch, California 8.95 Cabernet Sauvignon, The Federalist, California 11.95 Cabernet Sauvignon, Lake Sonoma, California 49.00 Malbec, Alta Vista \"Vive\", Argentina 7.95 Merlot, Spellbound, California 8.95 Pinot Noir, Elouan, Oregon 9.95 Pinot Noir, Fowles Wine, Australia 11.95 Pinot Noir Rosé, Villa Wolf, Pfalz, Germany 7.95 Red Blend, Clos de los Siete, Argentina 9.95 Red Blend, Conundrum, California 42.00 Red Zinfandel, Seghesio Family Vineyards, California 10.95 Disclaimer: Pricing and availability subject to change. \nKIDS\n\nKids Menu\n\nServed with fries and a beverage.\nChicken Strips 6.95 Cheeseburger 6.95 Fried Shrimp 6.95 Chicken Wings 6.95 Grilled Cheese 6.95 Fettuccine Alfredo 6.95 \n(no side)\nDisclaimer: Pricing and availability subject to change. \nDESSERT\n\nDesserts $9.95\nChocolate Brownie Apple Walnut Cobbler Croissant Bread Pudding Cheesecake Disclaimer: Pricing and availability subject to change. \nASHLEY PATIO\n\nApps\nShe Crab Soup 9.95 \nA rich and creamy Charleston classic\nSteamed Peel & Eat Shrimp \nOld Bay boil, served with cocktail sauce. GF\n\n1/2 lb\n13.95 Fried Crab Claws 17.95 \nServed with spicy cocktail sauce. Limited availability\nCalamari 16.95 \nLightly breaded, with marinara\nOysters Rockefeller (4) 17.95 \nSpinach, romano, bacon\nNashville Hot Wings 15.95 \nMarinated in hot pepper sauce, fried crispy, with bleu cheese dip\nOur Famous Croissants (5) 7.95 \nTopped with honey-butter\nBaked Potato Soup 8.95 \nCreamy soup topped with scallions, cheese, ham and bacon\n\nEntrees\nChicken Tenders Platter 19.95 \nFried chicken tenderloins, served with house-made honey BBQ sauce and french fries\nCrispy Shrimp Tacos (3) 17.95 \nJicama slaw, chipotle mayo, tomatoes, pickled onions, scallions, queso fresco\nShrimp + Grits 23.95 \nJumbo shrimp, andouille sausage, Adluh Mills grits\nFried Seafood Platter 28.95 \nShrimp, oysters, and flounder, served with french fries.\n\nSalads\nCalifornia Dreaming 15.95 \nMixed greens, ham and turkey, cheddar and monterey jack cheeses, egg, tomatoes, almonds topped with warm ham and bacon, house dressing\nRoasted Salmon or Chicken \nMixed greens, bacon, egg, avocado, tomatoes, balsamic vinaigrette\n\nRoasted Salmon\n18.95 \nChicken\n16.95 Caesar \nCrisp romaine with grated romano cheese and croutons\n\nChicken or Fried Shrimp\n15.95 \nFried Oysters\n17.95 \nSteaks + Ribs\n\nAged USDA Choice | Served with a house or caesar salad and side item. Rare - cold red center | Medium Rare - warm red center | Medium - hot red center | Medium Well - hot pink center | Well Done - brown center. Add broiled or fried shrimp to any steak +$7.95\nRibeye 39.95 \n14oz. hand cut with cajun butter. GF\nFilet Mignon 40.95 \n8oz. barrel cut. GF\nMarinated Sirloin 28.95 \n10oz. sirloin marinated in fruit juices, garlic, soy sauce and spices. GF\nBaby Back Ribs \nDanish full-flavored ribs, grilled with a charred exterior, basted with BBQ sauce, with side item. GF\n\nOne Rack\n23.95 \nTwo Racks\n31.95 \nSandwiches & Burgers\n\nServed with french fries\nSpicy Chicken Sandwich 16.95 \nCrispy fried chicken, american cheese, jicama slaw, pickles, chipotle mayo\nSteak Burger* 17.95 \n10 oz., shredded lettuce, pickles, red onion, tomato, cheddar cheese, our signature sauce\nBlackened Mahi Sandwich 17.95 \nToasted brioche, lemon, arugula, ripe tomato, curry mayonnaise, homemade pickles\n\nSides\nFrench Fries 5.95 Seasonal Veggie 5.95 Mashed Potatoes 5.95 Creamy Cole Slaw 5.95 Baked Potato 6.95 \n(after 4pm)\n\nDesserts $9.95\nChocolate Brownie Apple Walnut Cobbler Croissant Bread Pudding Cheesecake \nCocktails\n\nCocktails\nBarrel-Aged Old Fashioned 13.95 \nWild Turkey 101\nBlueberry Gin Smash 11.95 \nHat Trick gin, fresh blueberries, lemon, sugar\nCider Rules 12.95 \nSkyy vodka, all spice, lemon, apple cider, spiced apple bitters\n\nMargaritas\n\nPouring: Lunazul tequila\nClassic 10.95 \nAgave, lime\nSmoky Peach 10.95 \nIlegal mezcal, peach, agave, lime\nPineapple Jalapeño 10.95 \nPineapple, jalapeño, lime, triple sec\n\nFrozen Drinks\nCali Crush 10.95 \nParrot Bay Coconut rum, blue curacao, pineapple, house sour\nMojito 10.95 \nBacardi rum, mint, lime, sugar\n\nZero Proof\nCoconut Faux-Jito 9.95 \nNon-Alcoholic, Seedlip Spice 94, Coco Lopez, pineapple, lime, mint\nPineapple Spritz 9.95 \nNon-Alcoholic, Seedlip Grove 42, pineapple, lime, grenadine, cherry\n\nWine\n\nWhites\nChardonnay, EOS, California 7.95 Pinot Grigio, Lunardi, Italy 7.95 Sauvignon Blanc, Wairau River, New Zealand 8.95 \nReds\nCabernet Sauvignon, Firestone, Paso Robles 7.95 Malbec, Alta Vista \"Vive\", Argentina 7.95 Pinot Noir, Elouan, Oregon 9.95 \nBeer\n\nOn Tap\nBlue Moon 6.25 Creature Comforts 6.95 Michelob Ultra 5.95 Modelo Especial 6.25 \nBottles / Cans\nAustin Eastciders 4.95 Bud Light 5.25 Coors Banquet 5.95 Coors Light 5.25 Corona 5.25 Miller High Life Pony 3.95 PBR 3.95 White Claw 6.95 NA Athletic Upside Dawn 4.95 Disclaimer: Pricing and availability subject to change. See More Menus Menu | Reserve Augusta, GA Charleston, SC Columbia, SC Greenville, SC Spanish Fort, AL Surfside Beach, SC \nSign Up For Mailing List\nSelect your favorite location \nContact\nContact Catering CentraArchy Restaurants Join Our Team Gift Cards Sitemap \n© 2026 CentraArchy Restaurants. All Rights Reserved.",
      "hash": "27cda8354608",
      "downloadedAt": "2026-01-19T15:36:48.123Z",
      "trimmedAt": "2026-01-19T15:49:47.656Z",
      "sizeReduction": "89.7%"
    },
    {
      "url": "https://californiadreaming.rest/locations/",
      "text": "[Page Title: Order Online - California Dreaming]\n\nLocations + Menus Alabama Spanish Fort Georgia Augusta South Carolina Charleston Columbia Greenville Surside Beach Reserve Menu Order Online Order Online Home Happenings Gift Cards Order Online Contact Locations + Menus Alabama Spanish Fort Georgia Augusta South Carolina Charleston Columbia Greenville Surside Beach Reserve Menu Order Online Order Online Home Happenings Gift Cards Order Online Contact \nOrder Now\n\nAlabama\nSpanish Fort 30500 State Hwy 181 Spanish Fort, AL 36527 30500 State Hwy 181 Spanish Fort, AL 36527 | 251.626.9942 Menus Reservations Order Now Catering \nGeorgia\nAugusta 3241 Washington Rd. Augusta, GA 30907 3241 Washington Rd. Augusta, GA 30907 | 706.860.6206 Menus Reservations Order Now Catering \nSouth Carolina\nCharleston 1 Ashley Point Dr Charleston, SC 29407 1 Ashley Point Dr Charleston, SC 29407 | 843.766.1644 Menus Reservations Order Now Catering Columbia 401 South Main St. Columbia, SC 29201 401 South Main St. Columbia, SC 29201 | 803.254.6767 Menus Reservations Order Now Catering Greenville 40 Beacon Dr. Greenville, SC 29615 40 Beacon Dr. Greenville, SC 29615 | 864.234.9000 Menus Reservations Order Now Catering Surfside Beach 2657 Beaver Run Blvd Surfside Beach, SC 29575 2657 Beaver Run Blvd Surfside Beach, SC 29575 | 843.215.5255 Menus Reservations Order Now Catering Open Open Open Open Open Open Open Open Open Open Menu | Reserve Augusta, GA Charleston, SC Columbia, SC Greenville, SC Spanish Fort, AL Surfside Beach, SC \nSign Up For Mailing List\nSelect your favorite location \nContact\nContact Catering CentraArchy Restaurants Join Our Team Gift Cards Sitemap \n© 2026 CentraArchy Restaurants. All Rights Reserved.",
      "hash": "3c1ca1898e25",
      "downloadedAt": "2026-01-19T15:36:41.315Z",
      "trimmedAt": "2026-01-19T15:49:47.692Z",
      "sizeReduction": "98.8%"
    },
    {
      "url": "https://californiadreaming.rest/location/Augusta-GA/",
      "text": "[Page Title: Location - California Dreaming]\n\nLocations + Menus Alabama Spanish Fort Georgia Augusta South Carolina Charleston Columbia Greenville Surside Beach Reserve Menu Order Online Order Online Home Happenings Gift Cards Order Online Contact Locations + Menus Alabama Spanish Fort Georgia Augusta South Carolina Charleston Columbia Greenville Surside Beach Reserve Menu Order Online Order Online Home Happenings Gift Cards Order Online Contact \nAugusta, GA\n\nSince 1997, the well-liked, locally appreciated neighborhood place in Augusta, GA has been California Dreaming. The warm and inviting atmosphere with comfortable booth seating and open kitchen is great for families and date-nights alike. Specializing in high-quality, fresh ingredients like thick-cut steaks, tavern-style sandwiches, and of course, its namesake salad. Open for lunch and dinner, featuring patio dining and online ordering with curbside pickup.\nTo ensure the best experience for all guests, we seat groups of up to 6. 3241 Washington Rd. \n Augusta, GA 30907 Directions 706.860.6206 Order Now Reserve Hours Open Today Monday 11am-9pm Sunday 11am-9pm Open Today - Monday 11am-9pm Tuesday 11am-9pm Wednesday 11am-9pm Thursday 11am-9pm Friday 11am-10pm Saturday 11am-10pm \n|\nCatering Curbside to-go facebook instagram DINE \nDINE\n| \nDRINK\n| \nWINE\n| \nDESSERT\n| \nKIDS\n\nDINE\n\nApps\nShe Crab Soup 8.95 \nA rich and creamy Charleston classic\nSteamed Peel & Eat Shrimp 10.95 \n(9) Old Bay boil, served with cocktail sauce\nTraditional Nachos 13.95 \nChili, cheese, tomatoes, jalapenos, sour cream, house-made chips\nSeafood Nachos 17.95 \nSpicy shrimp, salmon, red onions, house-made chips, cheese sauce and lobster cream sauce with dill\nChicken Tenders 12.95 \nServed with house-made honey BBQ sauce\nTijuana or Nashville Hot Wings 15.95 \nMarinated in hot pepper sauce, fried crispy, with bleu cheese dip\nSouthwest Chicken Quesadilla 13.95 \nWith bacon & ham, mixed cheese, scallions, sour cream, and pico de gallo\nChili 8.95 \nTopped with cheese, scallions and sour cream, served with corn tortilla chips\nBaked Potato Soup 7.95 \nCreamy soup, scallions, cheese, ham, bacon\nOur Famous Croissants (5) 6.95 \nTopped with honey-butter\n\nEntrees\n\nAdd a house or caesar salad +$4.95\nCali Bowl \nWarm sushi rice, avocado, jalapenos, sesame seeds, mango, scallions, jicama slaw, pickled red onions, chipotle mayo. Choice of:\n\nTuna Poke\n17.95 \nMiso Salmon\n18.95 \nSteak\n18.95 \nFried Chicken\n15.95 Chicken Tenders Platter 16.95 \nFried chicken tenderloins, served with house-made honey BBQ sauce and french fries\nBlackened Chicken Pasta 17.95 \nAlfredo, scallions, tomatoes, with romano cheese\nKnob Hill Chicken 17.95 \nTopped with ham and monterey jack cheese, with side item\n\nSeafood Favorites\n\nAdd a house or caesar salad +$4.95\nShrimp San Francisco 17.95 \nMushrooms, garlic cream, white wine, served over pasta, topped with romano cheese\nMiso Salmon 25.95 \nMiso glazed, sweet soy, with side\nCarolina Trout 24.95 \nGrilled with arugula and lemon\nCrab Cakes 31.95 \nJumbo lump, mustard sauce, served with mashed potatoes and seasonal veggie\n\nFried Seafood Platters\n\nAll Three $26.95. Served with french fries\nShrimp 20.95 Oysters 24.95 Flounder 20.95 \nSalads\nCalifornia Dreaming 13.95 \nMixed greens, ham and turkey, cheddar and monterey jack cheeses, egg, tomatoes, almonds topped with warm ham and bacon, house dressing\nRoasted Salmon or Chicken \nMixed greens, bacon, egg, avocado, tomatoes, balsamic vinaigrette\n\nSalmon\n17.95 \nChicken\n15.95 Caesar \nCrisp romaine, grated romano cheese, croutons\n\nChicken or Fried Shrimp\n14.95 \nFried Oysters\n17.95 Chicken Club 15.95 \nMixed greens, fried chicken strips, avocado, bacon, egg, tomatoes, house-made ranch dressing\n\nSteaks, Chops + Ribs\n\nAged USDA Choice | Served with a house or caesar salad and side item\nPork Chop 26.95 \n16oz. double bone, frenched chop, peach jalapeno jam\nMarinated Sirloin 25.95 \n10oz. sirloin marinated in fruit juices, garlic, soy sauce and spices\nSteak + Shrimp 25.95 \nTwo 3oz. filet medallions, crispy fried shrimp\nRibeye 35.95 \n14oz. hand cut\nFilet Mignon 37.95 \n8oz. barrel cut\nBaby Back Ribs \nDanish full-flavored ribs, grilled with a charred exterior, basted with BBQ sauce, with side item\n\nOne Rack\n21.95 \nTwo Racks\n29.95 \nTacos (3)\n\nServed with side item\nChicken 15.95 \nShredded lettuce, chipotle & cilantro mayo, pico de gallo, monterey cheese\nSteak 17.95 \nCilantro cabbage slaw, chipotle mayo, pickled onions, queso fresco\nCrispy Shrimp 16.95 \nJicama slaw, chipotle mayo, tomatoes, pickled onions, scallions, queso fresco\n\nSandwiches\n\nServed with french fries\nAmerican Burger 12.95 \nLettuce, tomato, red onions, pickles and Duke's® mayo\nVeggie Burger 13.95 \nHouse-made, with pepper jack cheese, avocado, lettuce, tomato, BBQ molasses sauce, mayo and mustard\nSpicy Chicken 14.95 \nCrispy fried chicken, american cheese, jicama slaw, pickles, chipotle mayo\nClub 14.95 \nThinly sliced turkey, ham, bacon, cheddar and monterey jack cheeses, lettuce, tomato and mayo on toasted sourdough\nBlackened Mahi 16.95 \nToasted brioche, lemon arugula, ripe tomato, curry mayonnaise, homemade pickles\n\nSides\nFrench Fries 5.95 Seasonal Veggie 5.95 Cole Slaw 5.95 Mashed Potatoes 5.95 Baked Potato 6.95 \nafter 4pm\n\nDesserts\nChocolate Brownie 8.95 Apple Walnut Cobbler 8.95 Croissant Bread Pudding 8.95 Cheesecake 9.95 \nseasonal topping\nDisclaimer: Pricing and availability subject to change. \nDRINK\n\nCocktails\nBarrel-Aged Old Fashioned 13.95 \nElijah Craig Small Batch bourbon\nDreamsicle #3 10.95 \nEdmond's Honor whiskey, Licor 43, vanilla, orange juice\nSpritz-Mas 9.95 \nAperol, cranberry, lemon, prosecco\nHarvest Ember 10.95 \nEvan Williams bourbon, apple butter, lemon, spiced honey, apple wood smoke\n\nMargaritas\n\nPouring: Lunazul tequila\nClassic 10.95 \nAgave, lime\nSpiced Cranberry 10.95 \nWhite cranberry, cinnamon, lime, Cointreau\nSmoky Peach 10.95 \nIlegal mezcal, peach, agave, lime\nPineapple Jalapeño 10.95 \nPineapple, jalapeño, lime, triple sec\n\nMartinis\nToasted Marshmallow 11.95 \nHoodoo Espresso vodka, toasted marshmallow infusion\nSugar Cookie 11.95 \nBaileys, Absolut Vanilla vodka, di Amore amaretto\nStrawberry Rose 12.95 \nTito's vodka, rose essence, Chambord, strawberry\nDirty 13.95 \nGrey Goose vodka, olive brine, Dolin dry vermouth\n\nFrozen Drinks\n\n$10.95\nCali Crush \nParrot Bay Coconut rum, blue curacao, pineapple, house sour\nIrish Coffee \nJameson whiskey, Kahlua, cream, whipped cream\n\nZero Proof\nCoconut Faux-Jito 9.95 \nNon-Alcoholic, Seedlip Spice 94, Coco Lopez, pineapple, lime, mint\nPineapple Spritz 9.95 \nNon-Alcoholic, Seedlip Grove 42, pineapple, lime, grenadine, cherry\n\nSpirits\n\nBourbon / Whiskey\n2XO American Oak 14.95 Baby Jane 12.95 Buffalo Trace 10.95 Bulleit Rye 11.95 Jack Daniel's Single Barrel 11.95 Knob Creek 10.95 Maker's Mark 9.95 Old Soul 10.95 Peg Leg Porker 10.95 Redemption Rye 9.95 Redwood Empire Pipe Dream 14.95 Thirteenth Colony Southern Rye 11.95 WhistlePig 10yr Rye 21.95 Wild Turkey Special Reserve Rye 14.95 Woodford Reserve Double Oaked 15.95 \nTequila\nCasamigos Reposado 13.95 Clase Azul Reposado 28.95 Don Fulano Blanco 13.95 Don Julio Blanco 9.95 Don Julio Primavera Reposado 29.95 Espolon Blanco 9.95 G4 Blanco 14.95 Herradura Double Reposado 14.95 Lalo Blanco 13.95 Patron Silver 11.95 \nBeer\n\nOn Tap\nBlue Moon 6.25 Coors Light 5.95 Savannah River 6.25 Good Googly Moogly IPA 6.95 \nBottles / Cans\nAmberbock 4.95 Athletic N/A 5.95 Bud Light 4.95 Budweiser 4.95 Corona 5.25 Guinness 5.95 Heineken 5.25 Michelob Ultra 5.25 Miller Lite 4.95 Nutrl Seltzer 6.25 Sweetwater 420 5.25 Yuengling 5.25 Disclaimer: Pricing and availability subject to change. \nWINE\n\nWhites\nChardonnay, EOS, California 7.95 Chardonnay, Diora, Monterey 9.95 Chardonnay, Buehler, Russian River 11.95 Chardonnay, Frank Family, Carneros, California 55.00 Moscato, Seven Daughters, Italy 8.95 Moscato Rosé, Risata, Italy 7.95 Pinot Grigio, Lunardi, Italy 7.95 Prosecco, Riondo, Italy 8.95 Riesling, Loosen Bros. \"Dr L\" Mosel, Germany 7.95 Sauvignon Blanc, Wairau River, New Zealand 8.95 Sauvignon Blanc, Jax, California 10.95 Sparkling Wine, Poema, Cava 7.95 \nReds\nCabernet Sauvignon, Firestone, Paso Robles 7.95 Cabernet Sauvignon, Leese-Fitch, California 8.95 Cabernet Sauvignon, The Federalist, California 11.95 Cabernet Sauvignon, Lake Sonoma, California 49.00 Malbec, Alta Vista \"Vive\", Argentina 7.95 Merlot, Spellbound, California 8.95 Pinot Noir, Elouan, Oregon 9.95 Pinot Noir, Fowles Wine, Australia 11.95 Pinot Noir Rosé, Villa Wolf, Pfalz, Germany 7.95 Red Blend, Clos de los Siete, Argentina 9.95 Red Blend, Conundrum, California 42.00 Red Zinfandel, Seghesio Family Vineyards, California 10.95 Disclaimer: Pricing and availability subject to change. \nDESSERT\n\nDesserts\nChocolate Brownie 8.95 \nTopped with a Hershey's bar, served with vanilla ice cream.\nApple Walnut Cobbler 8.95 \nServed hot with vanilla ice cream.\nCroissant Bread Pudding 8.95 \nWarm croissants, raisins and creme anglaise, with vanilla ice cream and rum sauce.\nNew York Cheesecake 9.95 \nseasonal topping\nDisclaimer: Pricing and availability subject to change. \nKIDS\n\nKids Menu\n\nServed with fries and a beverage.\nChicken Strips 6.95 Cheeseburger 6.95 Fried Shrimp 6.95 Chicken Wings 6.95 Grilled Cheese 6.95 Fettuccine Alfredo 6.95 \n(no side)\nDisclaimer: Pricing and availability subject to change. See More Menus Menu | Reserve Augusta, GA Charleston, SC Columbia, SC Greenville, SC Spanish Fort, AL Surfside Beach, SC \nSign Up For Mailing List\nSelect your favorite location \nContact\nContact Catering CentraArchy Restaurants Join Our Team Gift Cards Sitemap \n© 2026 CentraArchy Restaurants. All Rights Reserved.",
      "hash": "8d02dca0cef7",
      "downloadedAt": "2026-01-19T15:36:42.918Z",
      "trimmedAt": "2026-01-19T15:49:47.776Z",
      "sizeReduction": "91.5%"
    },
    {
      "url": "https://californiadreaming.rest/location/Spanish-Fort-AL/",
      "text": "[Page Title: Location - California Dreaming]\n\nLocations + Menus Alabama Spanish Fort Georgia Augusta South Carolina Charleston Columbia Greenville Surside Beach Reserve Menu Order Online Order Online Home Happenings Gift Cards Order Online Contact Locations + Menus Alabama Spanish Fort Georgia Augusta South Carolina Charleston Columbia Greenville Surside Beach Reserve Menu Order Online Order Online Home Happenings Gift Cards Order Online Contact \nSpanish Fort, AL\n\nUniversally admired, California Dreaming in Spanish Fort, AL, located in the Eastern Shore outdoor shopping center, has been serving much-loved American classics since 2007. The consistent, hearty menu, lively bar-area – including tv’s for sports fans, and spacious patio, creates a welcoming atmosphere for everyone. Open for lunch and dinner with happy hour daily from 3PM and online ordering & curbside pickup.\nTo ensure the best experience for all guests, we seat groups of up to 8. While larger groups are seated separately, this arrangement is flexible during quieter hours. 30500 State Hwy 181 \n Spanish Fort, AL 36527 Directions 251.626.9942 Order Now Reserve Hours Open Today Monday 11am-9pm Sunday 11am-9pm Open Today - Monday 11am-9pm Tuesday 11am-9pm Wednesday 11am-9pm Thursday 11am-9pm Friday 11am-10pm Saturday 11am-10pm facebook instagram DINE \nDINE\n| \nDRINK\n| \nWINE\n| \nKIDS\n| \nDESSERT\n\nDINE\n\nApps\nShe Crab Soup 8.95 \nA rich and creamy Charleston classic\nSteamed Peel & Eat Shrimp 12.95 \n(9) Seasoned and served with cocktail sauce\nFried Crab Claws 16.95 \nServed with spicy cocktail sauce. (Limited availability)\nNashville Hot Wings 14.95 \nMarinated in hot pepper sauce, fried crispy, with bleu cheese dip\nChicken Tenders 12.95 \nServed with house-made honey BBQ sauce\nBaked Potato Soup 7.95 \nCreamy soup topped with scallions, cheese, ham and bacon\nOur Famous Croissants (5) 6.95 \nTopped with honey-butter\n\nNachos\n\nhouse-made chips\nTraditional 12.95 \nChili, cheese, tomatoes, jalapenos, sour cream\nBBQ Chicken 15.95 \nSmoky BBQ sauce, red onions, cheese sauce\nSeafood 16.95 \nSpicy shrimp, salmon, red onions, cheese sauce and lobster cream sauce with dill\n\nCali Bowl\nCali Bowl \nWarm sushi rice, avocado, jalapenos, sesame seeds, mango, scallions, jicama slaw, pickled red onions, chipotle mayo. Choice of:\n\nTuna Poke*\n17.95 \nMiso Salmon\n17.95 \nSteak\n18.95 \nFried Chicken\n15.95 \nEntrees\n\nAdd a house or caesar salad +$4.95\nChicken Tenders Platter 17.95 \nFried chicken tenderloins, served with house-made honey BBQ sauce and french fries\nBlackened Chicken Pasta 18.95 \nAlfredo, scallions, tomatoes, with romano cheese\nKnob Hill Chicken 18.95 \nTopped with ham and monterey jack cheese, with side item\n\nSeafood Favorites\n\nAdd a house or caesar salad +$4.95\nShrimp San Francisco 18.95 \nMushrooms, garlic cream, white wine, served over pasta, topped with romano cheese\nMiso Salmon 24.95 \nMiso glazed, sweet soy, with side\nFeatured Fish \nServed with a side item\n\nA.Q.\n\nFried Seafood Platters\n\nAll Three $25.95. Served with french fries\nShrimp 20.95 Oysters 24.95 Flounder 21.95 \nSalads\nCalifornia Dreaming 13.95 \nMixed greens, ham and turkey, cheddar and monterey jack cheeses, egg, tomatoes, almonds topped with warm ham and bacon, house dressing\nRoasted Salmon or Chicken \nMixed greens, bacon, egg, avocado, tomatoes, balsamic vinaigrette\n\nSalmon\n17.95 \nChicken\n14.95 Caesar \nCrisp romaine, grated romano cheese, croutons\n\nChicken or Fried Shrimp\n14.95 \nFried Oysters\n16.95 Chicken Club 14.95 \nMixed greens, fried chicken strips, avocado, bacon, egg, tomatoes, house-made ranch dressing\n\nSteaks, Chops + Ribs\n\nAged USDA Choice | Served with a house or caesar salad and side item\nCountry Fried Pork Chops 21.95 \nTwo pork chops fried crispy\nMarinated Sirloin* 25.95 \n10oz. sirloin marinated in fruit juices, garlic, soy sauce and spices\nSteak + Shrimp* 26.95 \nTwo 3oz. filet medallions, crispy fried shrimp\nRibeye* 36.95 \n14oz. hand cut\nNew York Strip* 36.95 \n14oz. center cut\nFilet Mignon* 37.95 \n8oz. barrel cut\nBaby Back Ribs \nDanish full-flavored ribs, grilled with a charred exterior, basted with BBQ sauce, with side item\n\nOne Rack\n21.95 \nTwo Racks\n28.95 \nTacos\n\nServed with side item\nChicken 15.95 \nShredded lettuce, chipotle & cilantro mayo, pico de gallo, Monterey cheese\nSteak 17.95 \nCilantro cabbage slaw, chipotle mayo, pickled onions, queso fresco\nCrispy Shrimp 16.95 \nJicama slaw, chipotle mayo, tomatoes, pickled onions, scallions, queso fresco\n\nSandwiches\n\nServed with french fries\nAmerican Burger* 12.95 \nLettuce, tomato, red onions, pickles and Duke's® mayo\nVeggie Burger 13.95 \nBeyond Burger,® sweet soy, Duke's® mayo, monterey jack cheese, lettuce, pickle, tomato and red onions\nSpicy Chicken 14.95 \nCrispy fried chicken, american cheese, jicama slaw, pickles, chipotle mayo\nChicken 13.95 \nBroiled, topped with jack cheese, bacon, arugula, tomato and honey mustard\nClub 13.95 \nThinly sliced turkey, ham, bacon, cheddar and monterey jack cheeses, lettuce, tomato and mayo on toasted sourdough\nCrispy Atlantic Flounder 15.95 \nTexas toast, dill and fried caper mayonnaise, pickles, shredded lettuce and red onion\n\nSides\nFrench Fries 4.95 Seasonal Veggie 4.95 Mashed Potatoes 4.95 Creamy Cole Slaw 4.95 Baked Potato 5.95 \nafter 4pm\n\nDesserts\nChocolate Brownie 8.95 Apple Walnut Cobbler 8.95 Croissant Bread Pudding 8.95 Cheesecake 8.95 \nseasonal topping\n\n*Denotes Cooked to Order | Consuming Raw or Undercooked Meats, Poultry, Seafood, Shellfish or Eggs May Increase Your Risk of Foodbourne Illness Especially if You Have Certain Medical Conditions. Gluten Free / Prepared in A Fryer with Wheat Ingredients\nDisclaimer: Pricing and availability subject to change. \nDRINK\n\nMargaritas\n\nPouring: Lunazul tequila\nClassic 10.95 \nAgave, lime\nSpiced Cranberry 10.95 \nWhite cranberry, cinnamon, lime, Cointreau\nSmoky Peach 10.95 \nIlegal mezcal, peach, agave, lime\nPineapple Jalapeño 10.95 \nPineapple, jalapeño, lime, triple sec\n\nCocktails\nBarrel-Aged Old Fashioned 13.95 \nElijah Craig Small Batch bourbon\nDreamsicle #3 10.95 \nEvan Williams bourbon, Licor 43, vanilla, orange juice\nSpritz-Mas 9.95 \nAperol, cranberry, lemon, prosecco\nHarvest Ember 10.95 \nEvan Williams bourbon, apple butter, lemon, spiced honey, apple wood smoke\n\nMartinis\nToasted Marshmallow 11.95 \nHoodoo Espresso vodka, toasted marshmallow infusion\nSugar Cookie 11.95 \nBaileys, Absolut Vanilla vodka, di Amore amaretto\nStrawberry Rose 12.95 \nTito's vodka, rose essence, Chambord, strawberry\nDirty 13.95 \nGrey Goose vodka, olive brine, Dolin dry vermouth\n\nFrozen Drinks\n\n$10.95\nCali Crush \nParrot Bay Coconut rum, blue curacao, pineapple, house sour\nIrish Coffee \nJameson whiskey, Kahlua, cream, whipped cream\n\nZero Proof\nCoconut Faux-Jito 9.95 \nNon-Alcoholic, Seedlip Spice 94, Coco Lopez, pineapple, lime, mint\nPineapple Spritz 9.95 \nNon-Alcoholic, Seedlip Grove 42, pineapple, lime, grenadine, cherry\n\nSpirits\n\nBourbon / Whiskey\nAngel Envy 13.95 Basil Hayden 12.95 Blade and Bow 12.95 Blanton's 18.95 Buffalo Trace 10.95 Eagle Rare 16.95 George Dickle 10.95 Jack Daniel's Single Barrel 10.95 Knob Creek 10.95 Makers Mark 10.95 Old Forrester 10.95 WhistlePig 6 Yr 13.95 Wild Turkey 101 10.95 Woodford Reserve Double Oaked 13.95 \nTequila\nCasamigos Anejo 14.95 Casamigos Blanco 12.95 Don Fulano Blanco 14.95 Don Julio Blanco 9.95 Espolon Blanco 9.95 Lalo Blanco 13.95 Mi Campo Reposado 12.95 Patron Silver 12.95 \nBeer\n\nOn Tap\nBlue Moon 6.95 Fairhope 6.95 Miller Lite 5.95 Modelo Draft 6.95 Yuengling 6.25 \nBottles / Cans\nAngry Orchard 5.95 Athletic N/A 5.95 Braided River Coastal Stout 6.95 Bud Light 4.95 Budweiser 4.95 Coors Light 4.95 Corona 5.95 Guinness 5.95 Heineken 5.95 Michelob Ultra 5.25 Miller Lite 4.95 Modelo Especial 5.95 New Castle 5.95 Nutrl Seltzer 5.95 Stella Artois 5.95 Disclaimer: Pricing and availability subject to change. \nWINE\n\nWhites\nChampagne, Moet & Chandon Imperial, France 90.00 Chardonnay, EOS, California 9.95 Moscato, Seven Daughters, Italy 7.95 Pinot Grigio, Lunardi, Italy 7.95 Prosecco, Riondo Prego Nero, Italy 9.95 Riesling, Loosen Bros. \"Dr L\" Mosel, Germany 7.95 Rosé, Charles Smith Band of Roses, California 7.95 Sauvignon Blanc, Jax, California 10.95 Sparkling Wine, Poema, Cava 7.95 \nReds\nCabernet Sauvignon, Firestone, Paso Robles 9.95 Cabernet Sauvignon, Oberon, Napa Valley 55.00 Cabernet Sauvignon, Quilt, Napa Valley 65.00 Merlot, Leese-Fitch, California 8.95 Pinot Noir, Elouan, Oregon 8.95 Pinot Noir, Fowles Wines, Australia 11.95 Pinot Noir, Belle Glos, Santa Lucia 65.00 Pinot Noir Rosé, Villa Wolf, Pfalz, Germany 7.95 Red Blend, Daou 'Pessimist', Paso Robles 11.95 Red Blend, Fess Parker, Santa Barbara 65.00 Red Zinfandel, Freakshow, Lodi 9.95 Disclaimer: Pricing and availability subject to change. \nKIDS\n\nKids Menu\n\nServed with fries and a beverage.\nChicken Strips 6.95 Cheeseburger 6.95 Fried Shrimp 6.95 Chicken Wings 6.95 Grilled Cheese 6.95 Fettuccine Alfredo 6.95 \n(no side)\nDisclaimer: Pricing and availability subject to change. \nDESSERT\n\nDesserts\nChocolate Brownie 8.95 Apple Walnut Cobbler 8.95 Croissant Bread Pudding 8.95 Cheesecake 9.95 \nseasonal topping\nDisclaimer: Pricing and availability subject to change. See More Menus Menu | Reserve Augusta, GA Charleston, SC Columbia, SC Greenville, SC Spanish Fort, AL Surfside Beach, SC \nSign Up For Mailing List\nSelect your favorite location \nContact\nContact Catering CentraArchy Restaurants Join Our Team Gift Cards Sitemap \n© 2026 CentraArchy Restaurants. All Rights Reserved.",
      "hash": "8fa27ce32765",
      "downloadedAt": "2026-01-19T15:36:42.093Z",
      "trimmedAt": "2026-01-19T15:49:47.844Z",
      "sizeReduction": "91.6%"
    },
    {
      "url": "https://californiadreaming.rest/location/Surfside-Beach-SC/",
      "text": "[Page Title: Location - California Dreaming]\n\nLocations + Menus Alabama Spanish Fort Georgia Augusta South Carolina Charleston Columbia Greenville Surside Beach Reserve Menu Order Online Order Online Home Happenings Gift Cards Order Online Contact Locations + Menus Alabama Spanish Fort Georgia Augusta South Carolina Charleston Columbia Greenville Surside Beach Reserve Menu Order Online Order Online Home Happenings Gift Cards Order Online Contact \nSurfside Beach, SC\n\nJoining the Myrtle Beach-area food scene in 2004, California Dreaming’s spacious, wide-open eatery in Surfside, SC has that winning combination of spirited, seaside atmosphere and comforting, hearty food. The American classics influenced menu – with fresh ingredients, is the restaurant anyone could love, from a family vacation spot to cozy date-night. Open for lunch and dinner with patio dining and convenient online ordering.\nTo ensure the best experience for all guests, we seat groups of up to 8. While larger groups are seated separately, this arrangement is flexible during quieter hours. 2657 Beaver Run Blvd \n Surfside Beach, SC 29575 Directions 843.215.5255 Order Now Reserve Hours Open Today Monday 11am-9pm Sunday 11am-9pm Open Today - Monday 11am-9pm Tuesday 11am-9pm Wednesday 11am-9pm Thursday 11am-9pm Friday 11am-9pm Saturday 11am-9pm \n|\nCatering Curbside to-go facebook instagram DINE \nDINE\n| \nDRINK\n| \nWINE\n| \nDESSERT\n| \nKIDS\n\nDINE\n\nApps\nShe Crab Soup 8.95 \nA rich and creamy Charleston classic\nSteamed Peel & Eat Shrimp 11.95 \n(9) Old Bay boil, served with cocktail sauce\nNashville Hot Wings 14.95 \nMarinated in hot pepper sauce, fried crispy, with bleu cheese dip\nChicken Tenders 12.95 \nServed with house-made honey BBQ sauce\nBaked Potato Soup 7.95 \nCreamy soup, scallions, cheese, ham, bacon\nChili 8.95 \nTopped with cheese, scallions and sour cream, served with corn tortilla chips\nOur Famous Croissants (5) 6.95 \nTopped with honey-butter\n\nNachos\n\nhouse-made chips\nTraditional 11.95 \nChili, cheese, tomatoes, jalapenos, sour cream\nBBQ Chicken 14.95 \nSmoky BBQ sauce, red onions, cheese sauce\nSeafood 16.95 \nSpicy shrimp, salmon, red onions, cheese sauce and lobster cream sauce with dill\n\nEntrees\n\nAdd a house or caesar salad +$4.95\nCali Bowl \nWarm sushi rice, avocado, jalapenos, sesame seeds, mango, scallions, jicama slaw, pickled red onions, chipotle mayo. Choice of:\n\nTuna Poke*\n16.95 \nMiso Salmon\n17.95 \nSteak\n17.95 \nFried Chicken\n14.95 Chicken Tenders Platter 17.95 \nFried chicken tenderloins, served with house-made honey BBQ sauce and french fries\nBlackened Chicken Pasta 17.95 \nAlfredo, scallions, tomatoes, with romano cheese\nKnob Hill Chicken 19.95 \nTopped with ham and monterey jack cheese, with side item\n\nSeafood Favorites\n\nAdd a house or caesar salad +$4.95\nShrimp San Francisco 17.95 \nMushrooms, garlic cream, white wine, served over pasta, topped with romano cheese\nRoasted Salmon 24.95 \nEncrusted with rosemary and thyme, with side item\nFeatured Fish \nServed with a side item\n\nA.Q.\n\nFried Seafood Platters\nFried Seafood Platters \nServed with french fries\n\nShrimp\n22.95 \nOysters\n24.95 \nFlounder\n22.95 \nAll Three\n27.95 \nSalads\nCalifornia Dreaming 14.95 \nMixed greens, ham and turkey, cheddar and monterey jack cheeses, egg, tomatoes, almonds topped with warm ham and bacon, house dressing\nRoasted Salmon or Chicken \nMixed greens, bacon, egg, avocado, tomatoes, balsamic vinaigrette\n\nSalmon\n16.95 \nChicken\n14.95 Caesar \nCrisp romaine, grated romano cheese, croutons\n\nChicken or Fried Shrimp\n14.95 \nFried Oysters\n16.95 Chicken Club 15.95 \nMixed greens, fried chicken strips, avocado, bacon, egg, tomatoes, house-made ranch dressing\n\nSteaks, Chops + Ribs\n\nAged USDA Choice | Served with a house or caesar salad and side item. Add broiled or fried shrimp to any steak +$6.95\nCountry Fried Pork Chops 20.95 \nTwo pork chops fried crispy\nMarinated Sirloin* 26.95 \n10oz. sirloin marinated in fruit juices, garlic, soy sauce and spices\nSteak + Shrimp* 26.95 \nTwo 3oz. filet medallions, crispy fried shrimp\nRibeye* 36.95 \n14oz. hand cut\nFilet Mignon* 38.95 \n8oz. barrel cut\nBaby Back Ribs \nDanish full-flavored ribs, grilled with a charred exterior, basted with BBQ sauce, with side item\n\nOne Rack\n20.95 \nTwo Racks\n28.95 \nTacos (3)\n\nServed with side item\nChicken 14.95 \nShredded lettuce, chipotle & cilantro mayo, pico de gallo, Monterey cheese\nSteak 17.95 \nCilantro cabbage slaw, chipotle mayo, pickled onions, queso fresco\nCrispy Shrimp 15.95 \nJicama slaw, chipotle mayo, tomatoes, pickled onions, scallions, queso fresco\n\nSandwiches\n\nServed with french fries\nAmerican Burger* 12.95 \nLettuce, tomato, red onions, pickles and Duke's® mayo\nVeggie Burger 13.95 \nHouse-made, with pepper jack cheese, avocado, lettuce, tomato, BBQ molasses sauce, mayo and mustard\nSpicy Chicken 14.95 \nCrispy fried chicken, american cheese, jicama slaw, pickles, chipotle mayo\nClub 12.95 \nThinly sliced turkey, ham, bacon, cheddar and monterey jack cheeses, lettuce, tomato and mayo on toasted sourdough\nChicken 13.95 \nBroiled, topped with jack cheese, bacon, shredded lettuce, tomato and honey mustard\n\nSides\nFrench Fries 4.95 Seasonal Veggie 4.95 Cole Slaw 4.95 Mashed Potatoes 4.95 Baked Potato 5.95 \nafter 4pm\n\nDesserts\nChocolate Brownie 8.95 Apple Walnut Cobbler 8.95 Croissant Bread Pudding 8.95 Cheesecake 9.95 \nseasonal topping\n\n*Denotes cooked to order | Gluten Free/Prepared in a fryer with wheat ingredients | Consuming raw or undercooked meats, poultry, seafood, shellfish or eggs may increase your risk of foodbourne illness especially if you have certain medical conditions\nDisclaimer: Pricing and availability subject to change. \nDRINK\n\nCocktails\nBarrel-Aged Old Fashioned 13.95 \nElijah Craig Small Batch bourbon\nDreamsicle #3 10.95 \nEvan Williams bourbon, Licor 43, vanilla, orange juice\nSpritz-Mas 9.95 \nAperol, cranberry, lemon, prosecco\nHarvest Ember 10.95 \nEvan Williams bourbon, apple butter, lemon, spiced honey, apple wood smoke\n\nMargaritas\n\nPouring: Lunazul tequila\nClassic 10.95 \nAgave, lime\nSpiced Cranberry 10.95 \nWhite cranberry, cinnamon, lime, Cointreau\nSmoky Peach 10.95 \nIlegal mezcal, peach, agave, lime\nPineapple Jalapeño 10.95 \nPineapple, jalapeño, lime, triple sec\n\nMartinis\nToasted Marshmallow 11.95 \nHoodoo Espresso vodka, toasted marshmallow infusion\nSugar Cookie 11.95 \nBaileys, Absolut Vanilla vodka, di Amore amaretto\nStrawberry Rose 12.95 \nTito's vodka, rose essence, Chambord, strawberry\nDirty 13.95 \nGrey Goose vodka, olive brine, Dolin dry vermouth\n\nFrozen Drinks\n\n$10.95\nCali Crush \nParrot Bay Coconut rum, blue curacao, pineapple, house sour\nIrish Coffee \nJameson whiskey, Kahlua, cream, whipped cream\n\nZero Proof\nCoconut Faux-Jito 9.95 \nNon-Alcoholic, Seedlip Spice 94, Coco Lopez, pineapple, lime, mint\nPineapple Spritz 9.95 \nNon-Alcoholic, Seedlip Grove 42, pineapple, lime, grenadine, cherry\n\nSpirits\n\nBourbon / Whiskey\nBaby Jane 14.95 Buffalo Trace 9.95 Bulleit Rye 8.95 Eagle Rare 10yr 15.95 Elijah Craig Toasted Barrel 8.95 Four Roses 8.95 Henry Mckenna 12.95 High West Double Rye 12.95 Jefferson's Ocean 15.95 Michter's Rye 12.95 Penelope Architect 15.95 Redwood Empire Emerald Giant Rye 12.95 Whistlepig Piggyback 16.95 Woodford Reserve 9.95 \nTequila\nCasamigos Reposado 13.95 Don Julio 1942 Añejo 26.95 Don Julio Blanco 9.95 Espolon Blanco 9.95 G4 Blanco 14.95 Herradura Reposado 12.95 Lalo Blanco 13.95 Partida Añejo 14.95 \nBeer\n\nOn Tap\nBlue Moon 6.95 Grand Strand Brewing Co 6.95 Michelob Ultra 5.95 Miller Light 5.95 Tidal Creek Brewhouse 6.95 Stella Artois 6.95 \nBottles / Cans\nAustin Eastciders 5.95 Bud / Bud Light 4.95 Coors Light 4.95 Corona 5.95 Corona Premier 5.95 New South Nut Brown Ale 5.95 New South White Ale 5.95 Voodoo Ranger IPA 5.95 Disclaimer: Pricing and availability subject to change. \nWINE\n\nWhites\nChardonnay, EOS, California 7.95 Chardonnay, Diora, Monterey 9.95 Chardonnay, Buehler, Russian River 11.95 Chardonnay, Frank Family, Carneros, California 55.00 Moscato, Seven Daughters, Italy 8.95 Moscato Rosé, Risata, Italy 7.95 Pinot Grigio, Lunardi, Italy 7.95 Prosecco, Riondo, Italy 8.95 Riesling, Loosen Bros. \"Dr L\" Mosel, Germany 7.95 Sauvignon Blanc, Wairau River, New Zealand 8.95 Sauvignon Blanc, Jax, California 10.95 Sparkling Wine, Poema, Cava 7.95 \nReds\nCabernet Sauvignon, Firestone, Paso Robles 7.95 Cabernet Sauvignon, Leese-Fitch, California 8.95 Cabernet Sauvignon, The Federalist, California 11.95 Cabernet Sauvignon, Lake Sonoma, California 49.00 Malbec, Alta Vista \"Vive\", Argentina 7.95 Merlot, Spellbound, California 8.95 Pinot Noir, Elouan, Oregon 9.95 Pinot Noir, Fowles Wine, Australia 11.95 Pinot Noir Rosé, Villa Wolf, Pfalz, Germany 7.95 Red Blend, Clos de los Siete, Argentina 9.95 Red Blend, Conundrum, California 42.00 Red Zinfandel, Seghesio Family Vineyards, California 10.95 Disclaimer: Pricing and availability subject to change. \nDESSERT\n\nDesserts\nChocolate Brownie 8.95 \nTopped with a Hershey's bar, served with vanilla ice cream.\nApple Walnut Cobbler 8.95 \nServed hot with vanilla ice cream.\nCroissant Bread Pudding 8.95 \nWarm croissants, raisins and creme anglaise, with vanilla ice cream and rum sauce.\nNew York Cheesecake 9.95 \nseasonal topping\nDisclaimer: Pricing and availability subject to change. \nKIDS\n\nKids Menu\n\nServed with fries and a beverage.\nChicken Strips 6.95 Cheeseburger 6.95 Fried Shrimp 6.95 Chicken Wings 6.95 Grilled Cheese 6.95 Fettuccine Alfredo 6.95 \n(no side)\nDisclaimer: Pricing and availability subject to change. See More Menus Menu | Reserve Augusta, GA Charleston, SC Columbia, SC Greenville, SC Spanish Fort, AL Surfside Beach, SC \nSign Up For Mailing List\nSelect your favorite location \nContact\nContact Catering CentraArchy Restaurants Join Our Team Gift Cards Sitemap \n© 2026 CentraArchy Restaurants. All Rights Reserved.",
      "hash": "a8d6dbd72ff2",
      "downloadedAt": "2026-01-19T15:36:45.338Z",
      "trimmedAt": "2026-01-19T15:49:47.915Z",
      "sizeReduction": "91.3%"
    },
    {
      "url": "https://californiadreaming.rest/location/Columbia-SC/",
      "text": "[Page Title: Location - California Dreaming]\n\nLocations + Menus Alabama Spanish Fort Georgia Augusta South Carolina Charleston Columbia Greenville Surside Beach Reserve Menu Order Online Order Online Home Happenings Gift Cards Order Online Contact Locations + Menus Alabama Spanish Fort Georgia Augusta South Carolina Charleston Columbia Greenville Surside Beach Reserve Menu Order Online Order Online Home Happenings Gift Cards Order Online Contact \nColumbia, SC\n\nLocated in downtown Columbia, SC, inside the historic 1902 Union Station, California Dreaming welcomes guests with its vibrant and inviting atmosphere. The restaurant's floor-to-ceiling windows offer a picturesque view of the rail tracks, stretching from the inactive platform to the main terminal. Paired with our hearty, made-from-scratch menu, it's no wonder California Dreaming has been a beloved local institution since 1984. Open for lunch and dinner daily, including online ordering with curbside pickup.\n\nCelebrating 40 years, California Dreaming has been a valued part of the Columbia community. Union Station, its historic home, was added to the National Register of Historic Places in 1973.\nPlease note that we provide Advance Priority Seating to reduce wait times and expedite the seating process when your entire party arrives. To ensure the best experience for all guests, we seat groups of up to 8. While larger groups are seated separately, this arrangement is flexible during quieter hours. 401 South Main St. \n Columbia, SC 29201 Directions 803.254.6767 Order Now Reserve Hours Open Today Monday 11am-9pm Sunday 11am-9pm Open Today - Monday 11am-9pm Tuesday 11am-9pm Wednesday 11am-9pm Thursday 11am-9pm Friday 11am-10pm Saturday 11am-10pm \n|\nCatering Curbside to-go facebook instagram DINE \nDINE\n| \nDRINK\n| \nWINE\n| \nKIDS\n| \nDESSERT\n\nDINE\n\nApps\nShe Crab Soup 9.95 \nA rich and creamy Charleston classic\nSteamed Peel & Eat Shrimp 10.95 \n(9) Old Bay boil, served with cocktail sauce\nFried Crab Claws 16.95 \nServed with spicy cocktail sauce. Llimited availability\nBBQ Chicken Nachos 15.95 \nSmoky BBQ sauce, red onions, house-made chips, cheese sauce\nSeafood Nachos 17.95 \nSpicy shrimp, salmon, red onions, house-made chips, cheese sauce and lobster cream sauce with dill\nNashville Hot Wings 15.95 \nMarinated in hot pepper sauce, fried crispy, with bleu cheese dip\nOur Famous Croissants (5) 6.95 \nTopped with honey-butter\nBaked Potato Soup 7.95 \nCreamy soup, scallions, cheese, ham, bacon\n\nEntrees\nCali Bowl \nWarm sushi rice, avocado, jalapenos, sesame seeds, mango, scallions, jicama slaw, pickled red onions, chipotle mayo. Choice of:\n\nTuna Poke\n17.95 \nMiso Salmon\n18.95 \nSteak\n18.95 \nFried Chicken\n15.95 Chicken Tenders Platter 17.95 \nFried chicken tenderloins, served with house-made honey BBQ sauce and french fries\nBlackened Chicken Pasta 17.95 \nAlfredo, scallions, tomatoes, with romano cheese\nKnob Hill Chicken 18.95 \nTopped with ham and monterey jack cheese, with side item\n\nSeafood Favorites\nMiso Salmon 24.95 \nMiso glazed, sweet soy, with side\nShrimp San Francisco 17.95 \nMushrooms, garlic cream, white wine, served over pasta, topped with romano cheese\nCarolina Trout 24.95 \nGrilled with arugula and lemon\n\nFried Seafood Platters\nShrimp 20.95 Oysters 24.95 Flounder 20.95 All Three 26.95 \nServed with french fries\n\nSalads\nCalifornia Dreaming 14.95 \nMixed greens, ham and turkey, cheddar and monterey jack cheeses, egg, tomatoes, almonds topped with warm ham and bacon, house dressing\nRoasted Salmon or Chicken \nMixed greens, bacon, egg, avocado, tomatoes, balsamic vinaigrette\n\nSalmon\n16.95 \nChicken\n15.95 Caesar \nCrisp romaine, grated romano cheese, croutons\n\nChicken or Fried Shrimp\n14.95 \nFried Oysters\n17.95 Chicken Club 15.95 \nMixed greens, fried chicken strips, avocado, bacon, egg, tomatoes, house-made ranch dressing\n\nSteaks, Chops + Ribs\n\nAged USDA Choice | Served with a house or caesar salad and side item\nPork Chop 26.95 \n16oz. double bone, frenched chop, peach jalapeno jam\nMarinated Sirloin 26.95 \n10oz. sirloin marinated in fruit juices, garlic, soy sauce and spices\nSteak + Shrimp 26.95 \nTwo 3oz. filet medallions, crispy fried shrimp\nRibeye 37.95 \n14oz. hand cut\nFilet Mignon 39.95 \n8oz. barrel cut\nBaby Back Ribs \nDanish full-flavored ribs, grilled with a charred exterior, basted with BBQ sauce, with side item\n\nOne Rack\n21.95 \nTwo Racks\n29.95 \nTacos (3)\n\nServed with side item\nChicken 15.95 \nShredded lettuce, chipotle & cilantro mayo, pico de gallo, Monterey cheese\nSteak 17.95 \nCilantro cabbage slaw, chipotle mayo, pickled onions, queso fresco\nCrispy Shrimp 16.95 \nJicama slaw, chipotle mayo, tomatoes, pickled onions, scallions, queso fresco\n\nSandwiches\n\nServed with french fries\nAmerican Burger 12.95 \nLettuce, tomato, red onions, pickles and Duke's® mayo\nVeggie Burger 13.95 \nHouse-made, pepper jack, avocado, lettuce, tomato, BBQ molasses sauce, mayo and mustard\nClub 13.95 \nThinly sliced turkey, ham, bacon, cheddar and monterey jack cheeses, lettuce, tomato and mayo on toasted sourdough\nSpicy Chicken 14.95 \nCrispy fried chicken, american cheese, jicama slaw, pickles, chipotle mayo\nChicken 14.95 \nBroiled, topped with jack cheese, bacon, arugula, tomato and honey mustard\n\nSides\nFrench Fries 5.95 Seasonal Veggie 5.95 Mashed Potatoes 5.95 Creamy Cole Slaw 5.95 Baked Potato 6.95 \nafter 4pm\n\nDesserts\nChocolate Brownie 8.95 Apple Walnut Cobbler 8.95 Croissant Bread Pudding 9.95 Cheesecake 9.95 \nseasonal topping\nDisclaimer: Pricing and availability subject to change. \nDRINK\n\nMargaritas\n\nPouring: Lunazul tequila\nClassic 10.95 \nAgave, lime\nSpiced Cranberry 10.95 \nWhite cranberry, cinnamon, lime, Cointreau\nSmoky Peach 10.95 \nIlegal mezcal, peach, agave, lime\nPineapple Jalapeño 10.95 \nPineapple, jalapeño, lime, triple sec\n\nCocktails\nBarrel-Aged Old Fashioned 13.95 \nElijah Craig Small Batch bourbon\nDreamsicle #3 10.95 \nEvan Williams bourbon, Licor 43, vanilla, orange juice\nSpritz-mas 9.95 \nAperol, cranberry, lemon, prosecco\nHarvest Ember 10.95 \nEvan Williams bourbon, apple butter, lemon, spiced honey, apple wood smoke\n\nMartinis\nToasted Marshmallow 11.95 \nHoodoo Espresso vodka, toasted marshmallow infusion\nSugar Cookie 11.95 \nBaileys, Absolut Vanilla vodka, di Amore amaretto\nStrawberry Rose 12.95 \nTito's vodka, rose essence, Chambord, strawberry\nDirty 13.95 \nGrey Goose vodka, olive brine, Dolin dry vermouth\n\nFrozen Drinks\n\n$10.95\nCali Crush \nParrot Bay Coconut rum, blue curacao, pineapple, house sour\nIrish Coffee \nJameson whiskey, Kahlua, cream, whipped cream\n\nZero Proof\nCoconut Faux-Jito 9.95 \nNon-Alcoholic, Seedlip Spice 94, Coco Lopez, pineapple, lime, mint\nPineapple Spritz 9.95 \nNon-Alcoholic, Seedlip Grove 42, pineapple, lime, grenadine, cherry\n\nSpirits\n\nBourbon / Whiskey\nBooker's Rye 18.95 Buffalo Trace 11.95 Bulleit Rye 10.95 Elijah Craig Toasted Barrel 10.95 Four Roses Small Batch 9.95 Henry McKenna 11.95 Jack Daniel's Bonded 11.95 Jefferson's Ocean 15.95 Knob Creek 10.95 Michter's Rye 10.95 Old Forester 1920 15.95 Penelope Toasted 14.95 Pikesville Rye 14.95 WhistlePig 10 Yr 21.95 Wild Turkey Longbranch 11.95 Woodford Reserve Double Oaked 12.95 \nTequila\nCasamigos Blanco 13.95 Don Julio Silver 10.95 El Tesoro Anejo 14.95 Espolon Blanco 10.95 Gran Centenario Cristalino 24.95 Herradura Reposado 13.95 Lalo Blanco 11.95 Ocho Plata Reposado 13.95 \nBeer\n\nOn Tap\nBlue Moon 6.25 Columbia Craft 6.25 Coors Banquet 5.95 Highland 6.95 Leinenkugel 6.25 Michelob Ultra 5.95 Sierra Nevada 6.95 Terrapin 6.25 Wicked Weed 6.25 Yuengling 6.25 \nBottles / Cans\nAthletic N/A 5.95 Austin Eastciders 6.95 Bud Light 4.95 Coors Light 4.95 Corona 4.95 Heineken 5.95 High Noon 7.25 High Rise Pineapple THC Seltzer 8.95 Miller Lite 4.95 Modelo 5.95 Not Beer Sparkling Water 5.95 Disclaimer: Pricing and availability subject to change. \nWINE\n\nWhites\nChardonnay, EOS, California 7.95 Chardonnay, Diora, Monterey 9.95 Chardonnay, Buehler, Russian River 11.95 Chardonnay, Frank Family, Carneros, California 55.00 Moscato, Seven Daughters, Italy 8.95 Moscato Rosé, Risata, Italy 7.95 Pinot Grigio, Lunardi, Italy 7.95 Prosecco, Riondo, Italy 8.95 Riesling, Loosen Bros. \"Dr L\" Mosel, Germany 7.95 Sauvignon Blanc, Wairau River, New Zealand 8.95 Sauvignon Blanc, Jax, California 10.95 Sparkling Wine, Poema, Cava 7.95 \nReds\nCabernet Sauvignon, Firestone, Paso Robles 7.95 Cabernet Sauvignon, Leese-Fitch, California 8.95 Cabernet Sauvignon, The Federalist, California 11.95 Cabernet Sauvignon, Lake Sonoma, California 49.00 Malbec, Alta Vista \"Vive\", Argentina 7.95 Merlot, Spellbound, California 8.95 Pinot Noir, Elouan, Oregon 9.95 Pinot Noir, Fowles Wine, Australia 11.95 Pinot Noir Rosé, Villa Wolf, Pfalz, Germany 7.95 Red Blend, Clos de los Siete, Argentina 9.95 Red Blend, Conundrum, California 42.00 Red Zinfandel, Seghesio Family Vineyards, California 10.95 Disclaimer: Pricing and availability subject to change. \nKIDS\n\nKids Menu\n\nServed with fries and a beverage.\nChicken Strips 6.95 Cheeseburger 6.95 Fried Shrimp 6.95 Chicken Wings 6.95 Grilled Cheese 6.95 Fettuccine Alfredo 6.95 \n(no side)\nDisclaimer: Pricing and availability subject to change. \nDESSERT\n\nDesserts\nChocolate Brownie 8.95 Apple Walnut Cobbler 8.95 Croissant Bread Pudding 9.95 Cheesecake 9.95 \nseasonal topping\nDisclaimer: Pricing and availability subject to change. See More Menus Menu | Reserve Augusta, GA Charleston, SC Columbia, SC Greenville, SC Spanish Fort, AL Surfside Beach, SC \nSign Up For Mailing List\nSelect your favorite location \nContact\nContact Catering CentraArchy Restaurants Join Our Team Gift Cards Sitemap \n© 2026 CentraArchy Restaurants. All Rights Reserved.",
      "hash": "cbc449480466",
      "downloadedAt": "2026-01-19T15:36:43.713Z",
      "trimmedAt": "2026-01-19T15:49:47.982Z",
      "sizeReduction": "91.6%"
    },
    {
      "url": "https://californiadreaming.rest/location/Charleston-SC/",
      "text": "[Page Title: Location - California Dreaming]\n\nLocations + Menus Alabama Spanish Fort Georgia Augusta South Carolina Charleston Columbia Greenville Surside Beach Reserve Menu Order Online Order Online Home Happenings Gift Cards Order Online Contact Locations + Menus Alabama Spanish Fort Georgia Augusta South Carolina Charleston Columbia Greenville Surside Beach Reserve Menu Order Online Order Online Home Happenings Gift Cards Order Online Contact \nCharleston, SC\n\nSince 1987, California Dreaming has been a proud part of the Charleston, SC community. Our spacious, open setting features floor-to-ceiling windows that offer stunning views of the Ashley River, creating the perfect backdrop for a lively night out. You can also enjoy these panoramic views from our wrap-around deck, complete with a bar and easily accessible by boat. Whether you're craving low country favorites or our famous prime rib, California Dreaming is a favorite among both locals and tourists.\nPlease note that we provide Advance Priority Seating to reduce wait times and expedite the seating process when your entire party arrives. To ensure the best experience for all guests, we seat groups of up to 6. While larger groups are seated separately, this arrangement is flexible during quieter hours. 1 Ashley Point Dr \n Charleston, SC 29407 Directions 843.766.1644 Order Now Reserve Hours Open Today Monday 4pm-9pm Sunday 11am-9pm Open Today - Monday 4pm-9pm Tuesday 4pm-9pm Wednesday 4pm-9pm Thursday 4pm-9pm Friday 4pm-10pm Saturday 11am-10pm \n|\nCatering Curbside to-go facebook instagram DINE \nDINE\n| \nDRINK\n| \nWINE\n| \nKIDS\n| \nDESSERT\n| \nASHLEY PATIO\n\nDINE\n\nApps\nShe Crab Soup 9.95 \nA rich and creamy Charleston classic\nSteamed Peel & Eat Shrimp \nOld Bay boil, served with cocktail sauce\n\n1/2lb\n13.95 Fried Crab Claws 17.95 \nServed with spicy cocktail sauce. Limited availability\nSeafood Nachos 18.95 \nSpicy shrimp, salmon, red onions, house-made chips, cheese sauce and lobster cream sauce with dill\nCreamed Spinach Nachos 13.95 \nwith house-made chips\nCalamari 16.95 \nLightly breaded, with marinara\nOysters Rockefeller (4) 17.95 \nSpinach, romano, bacon\nNashville Hot Wings 15.95 \nMarinated in hot pepper sauce, fried crispy, with bleu cheese dip\nChicken Tenders 13.95 \nServed with house-made honey BBQ sauce. cheese dip\nOur Famous Croissants (5) 7.95 \nTopped with honey-butter\nBaked Potato Soup 8.95 \nCreamy soup topped with scallions, cheese, ham and bacon\n\nEntrees\nThe Ashley 24.95 \nBroiled chicken breast, blackened shrimp, lobster cream sauce, served with a side\nRoasted Salmon 27.95 \nEncrusted with rosemary and thyme, served with mashed potatoes and seasonal veggie\nBlackened Chicken Pasta 19.95 \nAlfredo, scallions, tomatoes, with romano cheese\nChicken Tenders Platter 19.95 \nFried chicken tenderloins, served with house-made honey BBQ sauce and french fries\nCrispy Shrimp Tacos (3) 17.95 \nJicama slaw, chipotle mayo, tomatoes, pickled onions, scallions, queso fresco\n\nLow Country Favorites\n\nAdd a house or caesar salad +$5.95\nFirecracker Tuna* 32.95 \nThai glaze, served with mashed potatoes and seasonal veggie\nCrab Cakes 34.95 \nJumbo lump, mustard sauce, served with mashed potatoes and seasonal veggie\nFeatured Fish \nServed with a side item\n\nA.Q.\nCharleston Seafood Pasta 24.95 \nSautéed shrimp, mussels, garlic cream, white wine, romano\nShrimp + Grits 23.95 \nJumbo shrimp, andouille sausage, Adluh Mills grits\n\nFried Seafood Platters\nFried Seafood Platters \nServed with french fries\n\nShrimp\n21.95 \nOysters\n25.95 \nFlounder\n23.95 \nAll Three\n28.95 \nSalads\nCalifornia Dreaming 15.95 \nMixed greens, ham and turkey, cheddar and monterey jack cheeses, egg, tomatoes, almonds topped with warm ham and bacon, house dressing\nRoasted Salmon or Chicken \nMixed greens, bacon, egg, avocado, tomatoes, balsamic vinaigrette\n\nRoasted Salmon\n18.95 \nChicken\n16.95 Caesar \nCrisp romaine with grated romano cheese and croutons\n\nChicken or Fried Shrimp\n15.95 \nFried Oysters\n17.95 \nSteaks, Chops + Ribs\n\nAged USDA Choice | Served with a house or caesar salad and side item. Add broiled or fried shrimp to any steak +$7.95\nPork Chop 26.95 \n16oz. double bone, frenched chop, peach jalapeno jam\nNew York Strip* 39.95 \n14oz. center cut, garlic butter\nSurf + Turf* 34.95 \n10oz. ribeye topped with grilled garlic shrimp\nRibeye* 39.95 \n14oz. hand cut with cajun butter\nFilet Mignon* 40.95 \n8oz. barrel cut\nMarinated Sirloin* 28.95 \n10oz. sirloin marinated in fruit juices, garlic, soy sauce and spices\nBaby Back Ribs \nDanish full-flavored ribs, grilled with a charred exterior, basted with BBQ sauce, with side item\n\nOne Rack\n23.95 \nTwo Racks\n31.95 \nSandwiches & Burgers\n\nServed with french fries\nSpicy Chicken Sandwich 16.95 \nCrispy fried chicken, american cheese, jicama slaw, pickles, chipotle mayo\nNew Orleans Po'boy \nLettuce, tomato and tartar sauce on french bread\n\nFried Shrimp\n16.95 \nFried Oysters\n18.95 Steak Burger* 17.95 \n10 oz., shredded lettuce, pickles, red onion, tomato, cheddar cheese, our signature sauce\nBlackened Mahi Sandwich 17.95 \nToasted brioche, lemon, arugula, ripe tomato, curry mayonnaise, homemade pickles\n\nSides\nFrench Fries 5.95 Seasonal Veggie 5.95 Cole Slaw 5.95 Mashed Potatoes 5.95 Creamed Spinach 5.95 Baked Potato 6.95 \nafter 4pm\n\nDesserts\nChocolate Brownie 9.95 Apple Walnut Cobbler 9.95 Croissant Bread Pudding 9.95 Cheesecake 9.95 \nSeasonal Topping\n\nGluten free - prepared in a fryer with wheat ingredients. *Denotes cooked to order | consuming raw or undercooked meats, poultry, seafood, shellfish or eggs may increase your risk of foodbourne illness especially if you have certain medical conditions\nDisclaimer: Pricing and availability subject to change. \nDRINK\n\nCocktails\nBarrel-Aged Old Fashioned 14.95 \nMaker's Mark 'Living the Dream,' bitters, sugar\nDreamsicle #3 10.95 \nEvan Williams bourbon, Licor 43, vanilla, orange juice\nSpritz-Mas 9.95 \nAperol, cranberry, lemon, prosecco\nHarvest Ember 10.95 \nEvan Williams bourbon, apple butter, lemon, spiced honey, apple wood smoke\n\nMargaritas\n\nPouring: Jose Cuervo Tradicional\nClassic 10.95 \nAgave, lime\nSpiced Cranberry 10.95 \nWhite cranberry, cinnamon, lime, Cointreau\nSmoky Peach 10.95 \nIlegal mezcal, peach, agave, lime\nPineapple Jalapeño 10.95 \nPineapple, jalapeño, lime, triple sec\n\nMartinis\nToasted Marshmallow 11.95 \nHoodoo Espresso vodka, toasted marshmallow infusion\nSugar Cookie 11.95 \nBaileys, Absolut Vanilla vodka, di Amore amaretto\nStrawberry Rose 12.95 \nTito's vodka, rose essence, Chambord, strawberry\nDirty 13.95 \nGrey Goose vodka, olive brine, Dolin dry vermouth\n\nFrozen Drinks\nCali Crush 10.95 \nParrot Bay Coconut rum, blue curacao, pineapple, house sour\nIrish Coffee 10.95 \nJameson whiskey, Kahlua, cream, whipped cream\n\nZero Proof\nCoconut Faux-Jito 9.95 \nNon-Alcoholic, Seedlip Spice 94, Coco Lopez, pineapple, lime, mint\nPineapple Spritz 9.95 \nNon-Alcoholic, Seedlip Grove 42, pineapple, lime, grenadine, cherry\n\nSpirits\n\nBourbon / Whiskey\nBen Holladay 13.95 Bib & Tucker 10yr 15.95 High West High Country 16.95 Blanton's 18.95 Buffalo Trace 9.95 Bulleit Rye 8.95 Eagle Rare 10yr 15.95 Maker's Mark 'Living the Dream' 16.95 Michter's Rye 13.95 Old Forrester 1924 25.95 Old Pepper 11.95 Old Soul Tintype Series #1 19.95 Peerless Rye 19.95 Peg Leg Porker 9.95 Redwood Empire 12.95 Smoke Wagon 16.95 Traveller 13.95 \nTequila\n400 Conejos Mezcal 11.95 Casamigos Reposado 14.95 Don Julio Primavera 29.95 El Tesoro Añejo 13.95 Espolon Blanco 10.95 G4 Blanco 15.95 Herradura Legend 29.95 Lalo Blanco 12.95 Partida Añejo 15.95 Patron Roca Anejo 29.95 Tequila Ocho Plata 12.95 \nBeer\n\nOn Tap\nBlue Moon 6.25 Creature Comforts 6.95 Edmund's Oast 7.95 Michelob Ultra 5.95 Miller Lite 5.95 Modelo Especial 6.25 Southern Hops Blackwater Porter 6.95 \nBottles / Cans\nAustin Eastciders 6.95 Bud Light 5.25 Coors Light 5.25 Corona 5.25 Heineken 6.95 High Rise Pineapple THC Seltzer 9.95 PBR 3.95 Yuengling 5.95 White Claw 6.95 NA Athletic Upside Dawn 7.95 Disclaimer: Pricing and availability subject to change. \nWINE\n\nWhites\nChardonnay, EOS, California 7.95 Chardonnay, Diora, Monterey 9.95 Chardonnay, Buehler, Russian River 11.95 Chardonnay, Frank Family, Carneros, California 55.00 Moscato, Seven Daughters, Italy 8.95 Moscato Rosé, Risata, Italy 7.95 Pinot Grigio, Lunardi, Italy 7.95 Prosecco, Riondo, Italy 8.95 Riesling, Loosen Bros. \"Dr L\" Mosel, Germany 7.95 Sauvignon Blanc, Wairau River, New Zealand 8.95 Sauvignon Blanc, Jax, California 10.95 Sparkling Wine, Poema, Cava 7.95 \nReds\nCabernet Sauvignon, Firestone, Paso Robles 7.95 Cabernet Sauvignon, Leese-Fitch, California 8.95 Cabernet Sauvignon, The Federalist, California 11.95 Cabernet Sauvignon, Lake Sonoma, California 49.00 Malbec, Alta Vista \"Vive\", Argentina 7.95 Merlot, Spellbound, California 8.95 Pinot Noir, Elouan, Oregon 9.95 Pinot Noir, Fowles Wine, Australia 11.95 Pinot Noir Rosé, Villa Wolf, Pfalz, Germany 7.95 Red Blend, Clos de los Siete, Argentina 9.95 Red Blend, Conundrum, California 42.00 Red Zinfandel, Seghesio Family Vineyards, California 10.95 Disclaimer: Pricing and availability subject to change. \nKIDS\n\nKids Menu\n\nServed with fries and a beverage.\nChicken Strips 6.95 Cheeseburger 6.95 Fried Shrimp 6.95 Chicken Wings 6.95 Grilled Cheese 6.95 Fettuccine Alfredo 6.95 \n(no side)\nDisclaimer: Pricing and availability subject to change. \nDESSERT\n\nDesserts $9.95\nChocolate Brownie Apple Walnut Cobbler Croissant Bread Pudding Cheesecake Disclaimer: Pricing and availability subject to change. \nASHLEY PATIO\n\nApps\nShe Crab Soup 9.95 \nA rich and creamy Charleston classic\nSteamed Peel & Eat Shrimp \nOld Bay boil, served with cocktail sauce. GF\n\n1/2 lb\n13.95 Fried Crab Claws 17.95 \nServed with spicy cocktail sauce. Limited availability\nCalamari 16.95 \nLightly breaded, with marinara\nOysters Rockefeller (4) 17.95 \nSpinach, romano, bacon\nNashville Hot Wings 15.95 \nMarinated in hot pepper sauce, fried crispy, with bleu cheese dip\nOur Famous Croissants (5) 7.95 \nTopped with honey-butter\nBaked Potato Soup 8.95 \nCreamy soup topped with scallions, cheese, ham and bacon\n\nEntrees\nChicken Tenders Platter 19.95 \nFried chicken tenderloins, served with house-made honey BBQ sauce and french fries\nCrispy Shrimp Tacos (3) 17.95 \nJicama slaw, chipotle mayo, tomatoes, pickled onions, scallions, queso fresco\nShrimp + Grits 23.95 \nJumbo shrimp, andouille sausage, Adluh Mills grits\nFried Seafood Platter 28.95 \nShrimp, oysters, and flounder, served with french fries.\n\nSalads\nCalifornia Dreaming 15.95 \nMixed greens, ham and turkey, cheddar and monterey jack cheeses, egg, tomatoes, almonds topped with warm ham and bacon, house dressing\nRoasted Salmon or Chicken \nMixed greens, bacon, egg, avocado, tomatoes, balsamic vinaigrette\n\nRoasted Salmon\n18.95 \nChicken\n16.95 Caesar \nCrisp romaine with grated romano cheese and croutons\n\nChicken or Fried Shrimp\n15.95 \nFried Oysters\n17.95 \nSteaks + Ribs\n\nAged USDA Choice | Served with a house or caesar salad and side item. Rare - cold red center | Medium Rare - warm red center | Medium - hot red center | Medium Well - hot pink center | Well Done - brown center. Add broiled or fried shrimp to any steak +$7.95\nRibeye 39.95 \n14oz. hand cut with cajun butter. GF\nFilet Mignon 40.95 \n8oz. barrel cut. GF\nMarinated Sirloin 28.95 \n10oz. sirloin marinated in fruit juices, garlic, soy sauce and spices. GF\nBaby Back Ribs \nDanish full-flavored ribs, grilled with a charred exterior, basted with BBQ sauce, with side item. GF\n\nOne Rack\n23.95 \nTwo Racks\n31.95 \nSandwiches & Burgers\n\nServed with french fries\nSpicy Chicken Sandwich 16.95 \nCrispy fried chicken, american cheese, jicama slaw, pickles, chipotle mayo\nSteak Burger* 17.95 \n10 oz., shredded lettuce, pickles, red onion, tomato, cheddar cheese, our signature sauce\nBlackened Mahi Sandwich 17.95 \nToasted brioche, lemon, arugula, ripe tomato, curry mayonnaise, homemade pickles\n\nSides\nFrench Fries 5.95 Seasonal Veggie 5.95 Mashed Potatoes 5.95 Creamy Cole Slaw 5.95 Baked Potato 6.95 \n(after 4pm)\n\nDesserts $9.95\nChocolate Brownie Apple Walnut Cobbler Croissant Bread Pudding Cheesecake \nCocktails\n\nCocktails\nBarrel-Aged Old Fashioned 13.95 \nWild Turkey 101\nBlueberry Gin Smash 11.95 \nHat Trick gin, fresh blueberries, lemon, sugar\nCider Rules 12.95 \nSkyy vodka, all spice, lemon, apple cider, spiced apple bitters\n\nMargaritas\n\nPouring: Lunazul tequila\nClassic 10.95 \nAgave, lime\nSmoky Peach 10.95 \nIlegal mezcal, peach, agave, lime\nPineapple Jalapeño 10.95 \nPineapple, jalapeño, lime, triple sec\n\nFrozen Drinks\nCali Crush 10.95 \nParrot Bay Coconut rum, blue curacao, pineapple, house sour\nMojito 10.95 \nBacardi rum, mint, lime, sugar\n\nZero Proof\nCoconut Faux-Jito 9.95 \nNon-Alcoholic, Seedlip Spice 94, Coco Lopez, pineapple, lime, mint\nPineapple Spritz 9.95 \nNon-Alcoholic, Seedlip Grove 42, pineapple, lime, grenadine, cherry\n\nWine\n\nWhites\nChardonnay, EOS, California 7.95 Pinot Grigio, Lunardi, Italy 7.95 Sauvignon Blanc, Wairau River, New Zealand 8.95 \nReds\nCabernet Sauvignon, Firestone, Paso Robles 7.95 Malbec, Alta Vista \"Vive\", Argentina 7.95 Pinot Noir, Elouan, Oregon 9.95 \nBeer\n\nOn Tap\nBlue Moon 6.25 Creature Comforts 6.95 Michelob Ultra 5.95 Modelo Especial 6.25 \nBottles / Cans\nAustin Eastciders 4.95 Bud Light 5.25 Coors Banquet 5.95 Coors Light 5.25 Corona 5.25 Miller High Life Pony 3.95 PBR 3.95 White Claw 6.95 NA Athletic Upside Dawn 4.95 Disclaimer: Pricing and availability subject to change. See More Menus Menu | Reserve Augusta, GA Charleston, SC Columbia, SC Greenville, SC Spanish Fort, AL Surfside Beach, SC \nSign Up For Mailing List\nSelect your favorite location \nContact\nContact Catering CentraArchy Restaurants Join Our Team Gift Cards Sitemap \n© 2026 CentraArchy Restaurants. All Rights Reserved.",
      "hash": "dcda54cf9180",
      "downloadedAt": "2026-01-19T15:36:40.614Z",
      "trimmedAt": "2026-01-19T15:49:48.073Z",
      "sizeReduction": "89.7%"
    },
    {
      "url": "https://californiadreaming.rest/happenings/",
      "text": "[Page Title: Happenings - California Dreaming]\n\nLocations + Menus Alabama Spanish Fort Georgia Augusta South Carolina Charleston Columbia Greenville Surside Beach Reserve Menu Order Online Order Online Home Happenings Gift Cards Order Online Contact Locations + Menus Alabama Spanish Fort Georgia Augusta South Carolina Charleston Columbia Greenville Surside Beach Reserve Menu Order Online Order Online Home Happenings Gift Cards Order Online Contact With Love from California Dreaming Celebrate Valentine’s Weekend with Love from California Dreaming Dine-in reservations recommended | To Go available \n:  call: 706-760-8606 | :  call: 843-766-1644\nAugusta Reserve online, Charleston Reserve online, \n: call: 803-254-6767 | :  call: 864-234-9000,\nColumbia Reserve online, Greenville Reserve online, \n:   call: 843-215-5255 | : , call: 251-626-9942\nSurfside Beach Reserve online, Spanish Fort Reserve online Game On 🍗 Jan. 17 – Feb. 8 Game Day Wings Available January 17 – February 8 \nGame on. 3 lbs. of crispy jumbo chicken wings, tossed your way with four bold flavor options:Nashville Hot | House Buffalo | Sweet Chili | Tijuana — our classic dry-rub favorite\n\nChoose any two flavors per order. Served with fresh celery, ranch, and blue cheese dip.\nPro Tip: Available for pickup or dine-in. \n| | | | |\nOrder ahead for easy pickup: Augusta Charleston Columbia Greenville Spanish Fort Surfside Previous Happenings Menu | Reserve Augusta, GA Charleston, SC Columbia, SC Greenville, SC Spanish Fort, AL Surfside Beach, SC \nSign Up For Mailing List\nSelect your favorite location \nContact\nContact Catering CentraArchy Restaurants Join Our Team Gift Cards Sitemap \n© 2026 CentraArchy Restaurants. All Rights Reserved.",
      "hash": "ed0ef679b3da",
      "downloadedAt": "2026-01-19T15:36:47.359Z",
      "trimmedAt": "2026-01-19T15:49:48.087Z",
      "sizeReduction": "97.3%"
    },
    {
      "url": "https://californiadreaming.rest/location/Greenville-SC/",
      "text": "[Page Title: Location - California Dreaming]\n\nLocations + Menus Alabama Spanish Fort Georgia Augusta South Carolina Charleston Columbia Greenville Surside Beach Reserve Menu Order Online Order Online Home Happenings Gift Cards Order Online Contact Locations + Menus Alabama Spanish Fort Georgia Augusta South Carolina Charleston Columbia Greenville Surside Beach Reserve Menu Order Online Order Online Home Happenings Gift Cards Order Online Contact \nGreenville, SC\n\nSidle up to one of the bar stools overlooking the restaurant or grab a seat by window, the vibrant atmosphere at California Dreaming is inviting for families and date-nights alike. The large, open interior decked with limestone and expansive kitchen has a dedicated team cooking American classics from scratch daily. Don’t leave without ordering a thick-cut broiled steak or honey-butter croissants. Proudly serving the Greenville, SC community since 1991. Open for lunch and dinner daily, featuring patio seating as well as online ordering with curbside pickup.\nTo ensure the best experience for all guests, we seat groups of up to 8. While larger groups are seated separately, this arrangement is flexible during quieter hours. 40 Beacon Dr. \n Greenville, SC 29615 Directions 864.234.9000 Order Now Reserve Hours Open Today Monday 11am-9pm Sunday 11am-9pm Open Today - Monday 11am-9pm Tuesday 11am-9pm Wednesday 11am-9pm Thursday 11am-9pm Friday 11am-10pm Saturday 11am-10pm facebook instagram DINE \nDINE\n| \nDRINK\n| \nWINE\n| \nDESSERT\n| \nKIDS\n\nDINE\n\nApps\nShe Crab Soup 8.95 \nA rich and creamy Charleston classic\nSteamed Peel & Eat Shrimp 12.95 \n(9) Old Bay boil, served with cocktail sauce\nNashville Hot Wings 16.95 \nMarinated in hot pepper sauce, fried crispy, with bleu cheese dip\nChicken Tenders 12.95 \nServed with house-made honey BBQ sauce\nBaked Potato Soup 7.95 \nCreamy soup, scallions, cheese, ham, bacon\nChili 8.95 \nTopped with cheese, scallions and sour cream, served with corn tortilla chips\nOur Famous Croissants (5) 6.95 \nTopped with honey-butter\n\nNachos\n\nhouse-made chips\nTraditional 13.95 \nChili, cheese, tomatoes, jalapenos, sour cream\nBBQ Chicken 15.95 \nSmoky BBQ sauce, red onions, cheese sauce\nSeafood 17.95 \nSpicy shrimp, salmon, red onions, cheese sauce and lobster cream sauce with dill\n\nEntrees\nCali Bowl \nWarm sushi rice, avocado, jalapenos, sesame seeds, mango, scallions, jicama slaw, pickled red onions, chipotle mayo. Choice of:\n\nTuna Poke*\n17.95 \nMiso Salmon\n17.95 \nSteak\n18.95 \nFried Chicken\n15.95 Chicken Tenders Platter 17.95 \nFried chicken tenderloins, served with house-made honey BBQ sauce and french fries\nBlackened Chicken Pasta 18.95 \nAlfredo, scallions, tomatoes, with romano cheese\nKnob Hill Chicken 18.95 \nTopped with ham and monterey jack cheese, with side item\n\nSeafood Favorites\nMiso Salmon 25.95 \nMiso glazed, sweet soy, with side\nCarolina Trout 24.95 \nGrilled with arugula and lemon\nBaked Shrimp Alfredo 23.95 \nRoasted garlic alfredo, large shrimp, romano cheese and breadcrumbs\nCrab Cakes 31.95 \nJumbo lump, mustard sauce, served with mashed potatoes and seasonal veggie\n\nFried Seafood Platters\nShrimp 20.95 Oysters 24.95 Flounder 20.95 All Three 27.95 \nServed with french fries\n\nSalads\nCalifornia Dreaming 14.95 \nMixed greens, ham and turkey, cheddar and monterey jack cheeses, egg, tomatoes, almonds topped with warm ham and bacon, house dressing\nRoasted Salmon or Chicken \nMixed greens, bacon, egg, avocado, tomatoes, balsamic vinaigrette\n\nSalmon\n16.95 \nChicken\n15.95 Caesar \nCrisp romaine, grated romano cheese, croutons\n\nChicken or Fried Shrimp\n14.95 \nFried Oysters\n17.95 Chicken Club 15.95 \nMixed greens, fried chicken strips, avocado, bacon, egg, tomatoes, house-made ranch dressing\n\nSteaks, Chops + Ribs\n\nAged USDA Choice | Served with a house or caesar salad and side item. Add broiled or fried shrimp to any steak +$6.95\nPork Chop 26.95 \n16oz. double bone, frenched chop, peach jalapeno jam\nMarinated Sirloin* 26.95 \n10oz. sirloin marinated in fruit juices, garlic, soy sauce and spices\nFilet Mignon* 39.95 \n8oz. barrel cut\nSteak + Shrimp* 27.95 \nTwo 3oz. filet medallions, crispy fried shrimp\nRibeye* 38.95 \n14oz. hand cut with cajun butter\nNew York Strip* 38.95 \n14oz. center cut topped with garlic butter\nBaby Back Ribs \nDanish full-flavored ribs, grilled with a charred exterior, basted with BBQ sauce, with side item\n\nOne Rack\n21.95 \nTwo Racks\n29.95 \nTacos (3)\n\nServed with side item\nChicken 15.95 \nShredded lettuce, chipotle & cilantro mayo, pico de gallo, Monterey cheese\nSteak 17.95 \nCilantro cabbage slaw, chipotle mayo, pickled onions, queso fresco\nCrispy Shrimp 16.95 \nJicama slaw, chipotle mayo, tomatoes, pickled onions, scallions, queso fresco\n\nSandwiches\n\nServed with french fries\nDreaming Double* 15.95 \nDouble stack angus beef-blend, bacon, american cheese, pickles, signature sauce and onions\nVeggie Burger 13.95 \nHouse-made, pepper jack, avocado, lettuce, tomato, BBQ molasses sauce, mayo and mustard\nSpicy Chicken 14.95 \nNashville hot fried chicken, american cheese, jicama slaw, pickles, chipotle mayo\nClub 14.95 \nThinly sliced turkey, ham, bacon, cheddar and monterey jack cheeses, lettuce, tomato and mayo\nChicken 14.95 \nBroiled, topped with jack cheese, bacon, arugula, tomato and honey mustard\n\nSides\nFrench Fries 5.95 Seasonal Veggie 5.95 Cole Slaw 5.95 Mashed Potatoes 5.95 Baked Potato 6.95 \nafter 4pm\n\nDesserts\nChocolate Brownie 8.95 Apple Walnut Cobbler 8.95 Croissant Bread Pudding 8.95 Cheesecake 9.95 \nseasonal topping\n\n*Denotes cooked to order. Consuming raw or undercooked meats, poultry, seafood, shellfish or eggs may increase your risk of foodbourne illness especially if you have certain medical conditions. Gluten Free/Prepared in a fryer with wheat ingredients\nDisclaimer: Pricing and availability subject to change. \nDRINK\n\nCocktails\nBarrel-Aged Old Fashioned 13.95 \nElijah Craig Small Batch bourbon\nDreamsicle #3 10.95 \nEvan Williams bourbon, Licor 43, vanilla, orange juice\nSpritz-mas 9.95 \nAperol, cranberry, lemon, prosecco\nHarvest Ember 10.95 \nEvan Williams bourbon, apple butter, lemon, spiced honey, apple wood smoke\n\nMargaritas\n\nPouring - Lunazul tequila\nClassic 10.95 \nAgave, lime\nSpiced Cranberry 10.95 \nWhite cranberry, cinnamon, lime, Cointreau\nSmoky Peach 10.95 \nIlegal mezcal, peach, agave, lime\nPineapple Jalapeño 10.95 \nPineapple, jalapeño, lime, triple sec\n\nMartinis\nToasted Marshmallow 11.95 \nHoodoo Espresso vodka, toasted marshmallow infusion\nSugar Cookie 11.95 \nBaileys, Absolut Vanilla vodka, di Amore amaretto\nStrawberry Rose 12.95 \nTito's vodka, rose essence, Chambord, strawberry\nDirty 13.95 \nGrey Goose vodka, olive brine, Dolin dry vermouth\n\nFrozen Drinks\n\n$10.95\nCali Crush \nParrot Bay Coconut rum, blue curacao, pineapple, house sour\nIrish Coffee \nJameson whiskey, Kahlua, cream, whipped cream\n\nZero Proof\nCoconut Faux-Jito 9.95 \nNon-Alcoholic, Seedlip Spice 94, Coco Lopez, pineapple, lime, mint\nPineapple Spritz 9.95 \nNon-Alcoholic, Seedlip Grove 42, pineapple, lime, grenadine, cherry\n\nSpirits\n\nBourbon / Whiskey\nAngels Envy 13.95 Basil Hayden Straight 12.95 Blade & Bow 11.95 Buffalo Trace 11.95 Bulleit Rye 11.95 Eagle Rare 10 Year 15.95 Elijah Craig Small Batch 10.95 Four Roses Small Batch 9.95 Henry McKenna 13.95 Knob Creek 10.95 New Riff 14.95 Old Forester 10.95 Penelope Toasted 16.95 Redemption Rye 9.95 Redwood Empire Emerald Rye 13.95 Rittenhouse Rye 10.95 Widow Jane 10 Year 16.95 \nTequila\nCasamigos Blanco 13.95 Cazadores Anejo 15.95 Clase Azul Reposado 28.95 Don Julio Blanco 13.95 Espolon Blanco 10.95 Herradura Reposado 13.95 Lalo Blanco 12.95 Patron Silver 13.95 \nBeer\n\nOn Tap\nBlue Moon 6.25 Breckenridge Vanilla Porter 6.95 Coors Light 5.95 Michelob Ultra 5.95 Yuengling 6.25 \nBottles / Cans\nAngry Orchard 4.95 Bud Light 4.95 Corona 5.95 Heineken 5.25 Highland Pilsner 5.25 Highland Porter 5.25 Miller Lite 4.95 Stella Artois 5.25 Disclaimer: Pricing and availability subject to change. \nWINE\n\nWhites\nChardonnay, EOS, California 7.95 Chardonnay, Diora, Monterey 9.95 Chardonnay, Buehler, Russian River 11.95 Chardonnay, Frank Family, Carneros, California 55.00 Moscato, Seven Daughters, Italy 8.95 Moscato Rosé, Risata, Italy 7.95 Pinot Grigio, Lunardi, Italy 7.95 Prosecco, Riondo, Italy 8.95 Riesling, Loosen Bros. \"Dr L\" Mosel, Germany 7.95 Sauvignon Blanc, Wairau River, New Zealand 8.95 Sauvignon Blanc, Jax, California 10.95 Sparkling Wine, Poema, Cava 7.95 \nReds\nCabernet Sauvignon, Firestone, Paso Robles 7.95 Cabernet Sauvignon, Leese-Fitch, California 8.95 Cabernet Sauvignon, The Federalist, California 11.95 Cabernet Sauvignon, Lake Sonoma, California 49.00 Malbec, Alta Vista \"Vive\", Argentina 7.95 Merlot, Spellbound, California 8.95 Pinot Noir, Elouan, Oregon 9.95 Pinot Noir, Fowles Wine, Australia 11.95 Pinot Noir Rosé, Villa Wolf, Pfalz, Germany 7.95 Red Blend, Clos de los Siete, Argentina 9.95 Red Blend, Conundrum, California 42.00 Red Zinfandel, Seghesio Family Vineyards, California 10.95 Disclaimer: Pricing and availability subject to change. \nDESSERT\n\nDesserts\nChocolate Brownie 8.95 \nTopped with a Hershey's bar, served with vanilla ice cream.\nApple Walnut Cobbler 8.95 \nServed hot with vanilla ice cream.\nCroissant Bread Pudding 8.95 \nWarm croissants, raisins and creme anglaise, with vanilla ice cream and rum sauce.\nNew York Cheesecake 9.95 \nseasonal topping\nDisclaimer: Pricing and availability subject to change. \nKIDS\n\nKids Menu\n\nServed with fries and a beverage.\nChicken Strips 6.95 Cheeseburger 6.95 Fried Shrimp 6.95 Chicken Wings 6.95 Grilled Cheese 6.95 Fettuccine Alfredo 6.95 \n(no side)\nDisclaimer: Pricing and availability subject to change. See More Menus Menu | Reserve Augusta, GA Charleston, SC Columbia, SC Greenville, SC Spanish Fort, AL Surfside Beach, SC \nSign Up For Mailing List\nSelect your favorite location \nContact\nContact Catering CentraArchy Restaurants Join Our Team Gift Cards Sitemap \n© 2026 CentraArchy Restaurants. All Rights Reserved.",
      "hash": "f818c9615767",
      "downloadedAt": "2026-01-19T15:36:44.512Z",
      "trimmedAt": "2026-01-19T15:49:48.155Z",
      "sizeReduction": "91.3%"
    },
    {
      "url": "https://californiadreaming.rest/menu/",
      "text": "[Page Title: Order Online - California Dreaming]\n\nLocations + Menus Alabama Spanish Fort Georgia Augusta South Carolina Charleston Columbia Greenville Surside Beach Reserve Menu Order Online Order Online Home Happenings Gift Cards Order Online Contact Locations + Menus Alabama Spanish Fort Georgia Augusta South Carolina Charleston Columbia Greenville Surside Beach Reserve Menu Order Online Order Online Home Happenings Gift Cards Order Online Contact \nOrder Now\n\nAlabama\nSpanish Fort 30500 State Hwy 181 Spanish Fort, AL 36527 30500 State Hwy 181 Spanish Fort, AL 36527 | 251.626.9942 Menus Reservations Order Now Catering \nGeorgia\nAugusta 3241 Washington Rd. Augusta, GA 30907 3241 Washington Rd. Augusta, GA 30907 | 706.860.6206 Menus Reservations Order Now Catering \nSouth Carolina\nCharleston 1 Ashley Point Dr Charleston, SC 29407 1 Ashley Point Dr Charleston, SC 29407 | 843.766.1644 Menus Reservations Order Now Catering Columbia 401 South Main St. Columbia, SC 29201 401 South Main St. Columbia, SC 29201 | 803.254.6767 Menus Reservations Order Now Catering Greenville 40 Beacon Dr. Greenville, SC 29615 40 Beacon Dr. Greenville, SC 29615 | 864.234.9000 Menus Reservations Order Now Catering Surfside Beach 2657 Beaver Run Blvd Surfside Beach, SC 29575 2657 Beaver Run Blvd Surfside Beach, SC 29575 | 843.215.5255 Menus Reservations Order Now Catering Open Open Open Open Open Open Open Open Open Open Menu | Reserve Augusta, GA Charleston, SC Columbia, SC Greenville, SC Spanish Fort, AL Surfside Beach, SC \nSign Up For Mailing List\nSelect your favorite location \nContact\nContact Catering CentraArchy Restaurants Join Our Team Gift Cards Sitemap \n© 2026 CentraArchy Restaurants. All Rights Reserved.",
      "hash": "faca3f5677c8",
      "downloadedAt": "2026-01-19T15:36:46.598Z",
      "trimmedAt": "2026-01-19T15:49:48.188Z",
      "sizeReduction": "98.8%"
    }
  ],
  "sizeReduction": "93.2%"
}