{
  "venueId": "ChIJpeXs54xw_ogRDbs4R0aZQ5c",
  "venueName": "Comfort Inn & Suites Patriots Point",
  "venueArea": "Mount Pleasant",
  "website": "https://www.choicehotels.com/south-carolina/mount-pleasant/comfort-inn-hotels/sc064?mc=llgoxxpx",
  "scrapedAt": "2026-01-19T02:19:37.561Z",
  "trimmedAt": "2026-01-19T02:26:45.042Z",
  "pages": [
    {
      "url": "https://www.choicehotels.com/south-carolina/mount-pleasant/comfort-inn-hotels/sc064?mc=llgoxxpx",
      "text": "[Page Title: Challenge Page]",
      "hash": "8dc0674d7e21",
      "downloadedAt": "2026-01-19T02:10:56.433Z",
      "trimmedAt": "2026-01-19T02:26:45.042Z",
      "sizeReduction": "98.9%"
    }
  ],
  "sizeReduction": "98.9%"
}