{
  "venueId": "ChIJX4SGmHl8_ogRbTRIfJhMXIs",
  "venueName": "Buck's Pizza",
  "venueArea": "West Ashley",
  "website": "http://buckspizza.com/",
  "scrapedAt": "2026-01-19T15:41:59.703Z",
  "trimmedAt": "2026-01-19T15:45:58.165Z",
  "pages": [
    {
      "url": "http://buckspizza.com/",
      "text": "[Page Title: Home - Buck's Pizza]\n\nHOME Locations About Blog Contact Franchise Information \nCheck your local Buck's for\n\nDine-in | Curbside | Delivery | Drive-thru\nHOME Locations About Blog Contact Franchise Information Find My Buck's \nBuck's Pizza\nFIND US NEAR YOU \nGOOD | BETTER | BUCKS\n\nEveryone loves delicious food, especially pizza, but with today’s hectic life, you probably don’t have time to prepare a home-cooked meal. That’s where Buck’s Pizza comes in.\n\nBucks Pizza offers menu choices of pasta, wings, salads, sandwiches, desserts & the Best PIZZA using the freshest ingredients served at the peak of deliciousness.\n\nWhether you crave pizza made with handmade dough and carefully selected tomatoes, hot and crispy chicken tenders, or even a healthy salad, our menu has something sure to please even the pickiest eaters.\nLocations & Menus \nChecking on your order?\n\nFor faster service placing an order or to check on an order, please contact your local Buck's.\nLocations \nGOOD | BETTER | BUCKS\n\nUsing the freshest ingredients served at the peak of deliciousness.\n\nDelicious since 1994\nHOME LOCATIONS ABOUT BLOG CONTACT FRANCHISE INFORMATION \nWebsite Built by Magnus Marketing",
      "hash": "86d629ea6032",
      "downloadedAt": "2026-01-19T15:36:35.023Z",
      "trimmedAt": "2026-01-19T15:45:58.143Z",
      "sizeReduction": "99.0%"
    },
    {
      "url": "https://buckspizza.com/locations/",
      "text": "[Page Title: Find a Buck's Pizza location near you!]\n\nHOME Locations About Blog Contact Franchise Information \nCheck your local Buck's for\n\nDine-in | Curbside | Delivery | Drive-thru\nHOME Locations About Blog Contact Franchise Information Find My Buck's Locations \nPeachtree, GA\n\nGloversville, NY\n\nMorganton, NC\n\nTryon, NC\n\nClearfield, PA\n\nDuBois, PA\n\nSt. Marys, PA\n\nCharleston, SC\n\nLexington, SC\n\nWalterboro, SC\n\nHidalgo, TX\n\nMont Belvieu, TX\n\nClear Lake, TX\n\nOpen your own Franchise!\n\nBuffalo, MN\n\nMission, TX\n\nHidalgo, TX\n\nAntigo, WI\n\nGOOD | BETTER | BUCKS\n\nUsing the freshest ingredients served at the peak of deliciousness.\n\nDelicious since 1994\nHOME LOCATIONS ABOUT BLOG CONTACT FRANCHISE INFORMATION \nWebsite Built by Magnus Marketing\nPrivacy Policy",
      "hash": "ebda6607523d",
      "downloadedAt": "2026-01-19T15:36:37.145Z",
      "trimmedAt": "2026-01-19T15:45:58.165Z",
      "sizeReduction": "99.6%"
    }
  ],
  "sizeReduction": "99.4%"
}