{
  "venueId": "ChIJ52y8nhh9_ogRZTwlCy01DHI",
  "venueName": "Jade Garden",
  "venueArea": "West Ashley",
  "website": "http://jadegardencharleston.weebly.com/",
  "scrapedAt": "2026-01-19T15:41:54.943Z",
  "trimmedAt": "2026-01-19T15:42:37.815Z",
  "pages": [
    {
      "url": "http://jadegardencharleston.weebly.com/",
      "text": "[Page Title: Jade Garden Chinese Restaurant - Home Page]\n\nJade Garden Chinese Restaurant Home Page Lunch Special Dinner Special Fried Dishes Appetizers Soup Chow Mein Fried Rice Lo Mein Chow Mein Fun ( Pancit ) Moo Shu Beef Roast Pork Chicken Shrimp Egg Foo Young Sweet & Sour Vegetable Bean Curd ( Tofu ) Special Diet Chef's Specialties Side Orders Questions / Comments Picture Page Jade Garden Chinese Restaurant Address: 3125 Bees Ferry Road Suite A2 Charleston, SC 29414 (inside Bi-Lo Shopping Center at HWY 61) Phone #: (843) 766 - 0666 Business Hours Monday - Thursday 11:30 AM - 9:30 PM Friday - Saturday 11:30 AM - 10:30 PM Sunday 3:00 PM - 9:30 PM \nPayment Acceptance :\nCASH Visitor Tracker \nPowered by\nCreate your own unique website with customizable templates. Get Started",
      "hash": "4d32834524c0",
      "downloadedAt": "2026-01-19T15:37:07.334Z",
      "trimmedAt": "2026-01-19T15:42:37.815Z",
      "sizeReduction": "97.5%"
    }
  ],
  "sizeReduction": "97.5%"
}